{
  "video_id": "tMCLAs3APrE",
  "language": "English (auto-generated)",
  "language_code": "en",
  "subtitles": [
    {
      "text": "hated about this i got my celery stacked",
      "start": 0.0,
      "duration": 3.28
    },
    {
      "text": "up",
      "start": 2.32,
      "duration": 2.479
    },
    {
      "text": "sitting right here i know you guys might",
      "start": 3.28,
      "duration": 3.519
    },
    {
      "text": "not be able to see it but there it is",
      "start": 4.799,
      "duration": 6.241
    },
    {
      "text": "and i got lots of celery back here too",
      "start": 6.799,
      "duration": 7.041
    },
    {
      "text": "so i'm really excited and i'll try to",
      "start": 11.04,
      "duration": 4.4
    },
    {
      "text": "answer some questions as i'm doing this",
      "start": 13.84,
      "duration": 2.24
    },
    {
      "text": "too",
      "start": 15.44,
      "duration": 3.2
    },
    {
      "text": "um just got letting you guys know you",
      "start": 16.08,
      "duration": 4.08
    },
    {
      "text": "know about the black friday sale so i",
      "start": 18.64,
      "duration": 3.12
    },
    {
      "text": "just didn't want anybody to",
      "start": 20.16,
      "duration": 3.92
    },
    {
      "text": "lose out on a chance to get the juicer",
      "start": 21.76,
      "duration": 4.16
    },
    {
      "text": "for the this is an incredible celery",
      "start": 24.08,
      "duration": 3.68
    },
    {
      "text": "juicer okay so just wanted you wanted to",
      "start": 25.92,
      "duration": 3.759
    },
    {
      "text": "make sure you had a chance to",
      "start": 27.76,
      "duration": 3.439
    },
    {
      "text": "maybe get it if you wanted to pick one",
      "start": 29.679,
      "duration": 5.121
    },
    {
      "text": "up um it's the mm-900",
      "start": 31.199,
      "duration": 5.841
    },
    {
      "text": "hds celery juicer that's the one",
      "start": 34.8,
      "duration": 3.919
    },
    {
      "text": "specifically it also juices everything",
      "start": 37.04,
      "duration": 2.32
    },
    {
      "text": "else too",
      "start": 38.719,
      "duration": 3.041
    },
    {
      "text": "hello hi alyssa great to see you glad",
      "start": 39.36,
      "duration": 3.6
    },
    {
      "text": "you're coming on here",
      "start": 41.76,
      "duration": 3.92
    },
    {
      "text": "hello from vienna awesome great michelle",
      "start": 42.96,
      "duration": 3.919
    },
    {
      "text": "l good to see you",
      "start": 45.68,
      "duration": 3.44
    },
    {
      "text": "awesome glad you guys are coming on",
      "start": 46.879,
      "duration": 4.081
    },
    {
      "text": "incredible",
      "start": 49.12,
      "duration": 4.24
    },
    {
      "text": "how you said hello to the cj king that's",
      "start": 50.96,
      "duration": 3.279
    },
    {
      "text": "funny",
      "start": 53.36,
      "duration": 2.24
    },
    {
      "text": "um you're making your glenda you're",
      "start": 54.239,
      "duration": 3.041
    },
    {
      "text": "making your batch now",
      "start": 55.6,
      "duration": 4.959
    },
    {
      "text": "40 ounces nice josh you're on here",
      "start": 57.28,
      "duration": 6.64
    },
    {
      "text": "great great so great um",
      "start": 60.559,
      "duration": 5.361
    },
    {
      "text": "so it's good to see you guys from",
      "start": 63.92,
      "duration": 4.48
    },
    {
      "text": "portugal too whoa",
      "start": 65.92,
      "duration": 6.16
    },
    {
      "text": "netherlands right on this is great",
      "start": 68.4,
      "duration": 5.52
    },
    {
      "text": "love to see you guys here it's awesome",
      "start": 72.08,
      "duration": 3.44
    },
    {
      "text": "greetings from germany",
      "start": 73.92,
      "duration": 4.96
    },
    {
      "text": "cool cool so i got the mm 900 hds right",
      "start": 75.52,
      "duration": 4.239
    },
    {
      "text": "here i'm gonna do",
      "start": 78.88,
      "duration": 3.44
    },
    {
      "text": "celery that's what i'm gonna do and i'm",
      "start": 79.759,
      "duration": 3.601
    },
    {
      "text": "gonna show you something it's really",
      "start": 82.32,
      "duration": 2.24
    },
    {
      "text": "cool because everybody's totally",
      "start": 83.36,
      "duration": 2.64
    },
    {
      "text": "freaking out about the pulp",
      "start": 84.56,
      "duration": 5.519
    },
    {
      "text": "thing about how virtually i had no pulp",
      "start": 86.0,
      "duration": 6.32
    },
    {
      "text": "and it was dry to the bone and i had",
      "start": 90.079,
      "duration": 3.841
    },
    {
      "text": "this much celery juice",
      "start": 92.32,
      "duration": 4.32
    },
    {
      "text": "and that's because this specific model",
      "start": 93.92,
      "duration": 4.08
    },
    {
      "text": "there's other models that look like this",
      "start": 96.64,
      "duration": 3.6
    },
    {
      "text": "from omega but it's not this",
      "start": 98.0,
      "duration": 4.72
    },
    {
      "text": "model this has a device here at the end",
      "start": 100.24,
      "duration": 4.64
    },
    {
      "text": "that actually makes it so it squeezes",
      "start": 102.72,
      "duration": 2.56
    },
    {
      "text": "almost",
      "start": 104.88,
      "duration": 3.599
    },
    {
      "text": "every last drop out of that celery so",
      "start": 105.28,
      "duration": 5.199
    },
    {
      "text": "it's saving money like this year alone i",
      "start": 108.479,
      "duration": 3.92
    },
    {
      "text": "know i saved a ton of money half the",
      "start": 110.479,
      "duration": 2.881
    },
    {
      "text": "celery cost",
      "start": 112.399,
      "duration": 2.72
    },
    {
      "text": "easy half the celery cost so i'm not",
      "start": 113.36,
      "duration": 3.039
    },
    {
      "text": "throwing away my",
      "start": 115.119,
      "duration": 3.441
    },
    {
      "text": "my my celery juice through the pulp and",
      "start": 116.399,
      "duration": 3.601
    },
    {
      "text": "stuff or whatever discarding it or",
      "start": 118.56,
      "duration": 2.0
    },
    {
      "text": "throwing",
      "start": 120.0,
      "duration": 3.04
    },
    {
      "text": "throwing it in the garden or whatever",
      "start": 120.56,
      "duration": 4.08
    },
    {
      "text": "and then the juice goes with it",
      "start": 123.04,
      "duration": 4.079
    },
    {
      "text": "so what's amazing about this is this",
      "start": 124.64,
      "duration": 4.08
    },
    {
      "text": "machine is squeezing it out and i'm",
      "start": 127.119,
      "duration": 2.48
    },
    {
      "text": "going to show you how to i'm going to",
      "start": 128.72,
      "duration": 1.759
    },
    {
      "text": "show you how to do it and i'm going to",
      "start": 129.599,
      "duration": 2.481
    },
    {
      "text": "show you how the pulp works we're",
      "start": 130.479,
      "duration": 3.441
    },
    {
      "text": "literally it's just a handful of this",
      "start": 132.08,
      "duration": 2.879
    },
    {
      "text": "dry pull",
      "start": 133.92,
      "duration": 2.64
    },
    {
      "text": "i showed you guys the other day it was",
      "start": 134.959,
      "duration": 3.761
    },
    {
      "text": "insane i mean filled up with all the",
      "start": 136.56,
      "duration": 4.319
    },
    {
      "text": "celery juice and a little bit of pulp",
      "start": 138.72,
      "duration": 5.68
    },
    {
      "text": "good to see you guys glad you're here um",
      "start": 140.879,
      "duration": 5.521
    },
    {
      "text": "i think i'm gonna drink a little bit of",
      "start": 144.4,
      "duration": 3.6
    },
    {
      "text": "lemon balm tea for the moment because",
      "start": 146.4,
      "duration": 3.36
    },
    {
      "text": "i've been talking all morning",
      "start": 148.0,
      "duration": 4.56
    },
    {
      "text": "oh my god it never stops so glad you",
      "start": 149.76,
      "duration": 3.52
    },
    {
      "text": "guys",
      "start": 152.56,
      "duration": 2.56
    },
    {
      "text": "are coming on it's so easy to use and",
      "start": 153.28,
      "duration": 4.0
    },
    {
      "text": "clean did you see that this model is so",
      "start": 155.12,
      "duration": 4.32
    },
    {
      "text": "easy i just saw that comment",
      "start": 157.28,
      "duration": 4.4
    },
    {
      "text": "to use and clean it's it's unbelievable",
      "start": 159.44,
      "duration": 3.2
    },
    {
      "text": "so it's 60",
      "start": 161.68,
      "duration": 4.4
    },
    {
      "text": "off it's 20 percent 20 off black friday",
      "start": 162.64,
      "duration": 5.319
    },
    {
      "text": "sale omega",
      "start": 166.08,
      "duration": 4.56
    },
    {
      "text": "juicers.com link should be there",
      "start": 167.959,
      "duration": 7.441
    },
    {
      "text": "in the description so omega omega",
      "start": 170.64,
      "duration": 9.16
    },
    {
      "text": "juicers.com this is the mm-900",
      "start": 175.4,
      "duration": 7.4
    },
    {
      "text": "hds so the mm-900",
      "start": 179.8,
      "duration": 5.48
    },
    {
      "text": "hds celery juicer just letting you know",
      "start": 182.8,
      "duration": 4.079
    },
    {
      "text": "hello from finland cool cool so i'm",
      "start": 185.28,
      "duration": 3.36
    },
    {
      "text": "going to make some celery juice",
      "start": 186.879,
      "duration": 3.28
    },
    {
      "text": "i'm going to talk about the benefits too",
      "start": 188.64,
      "duration": 3.04
    },
    {
      "text": "you love yours jody",
      "start": 190.159,
      "duration": 4.481
    },
    {
      "text": "cool you're using one awesome that's",
      "start": 191.68,
      "duration": 4.4
    },
    {
      "text": "amazing",
      "start": 194.64,
      "duration": 3.2
    },
    {
      "text": "that's so good you guys it's worth it",
      "start": 196.08,
      "duration": 3.28
    },
    {
      "text": "because it saves money because that's",
      "start": 197.84,
      "duration": 3.28
    },
    {
      "text": "how i look at it to you it's like",
      "start": 199.36,
      "duration": 4.48
    },
    {
      "text": "this juicer right here has paid for",
      "start": 201.12,
      "duration": 3.52
    },
    {
      "text": "itself",
      "start": 203.84,
      "duration": 3.039
    },
    {
      "text": "so it's paid for itself that's what it's",
      "start": 204.64,
      "duration": 4.08
    },
    {
      "text": "done you know my other juicers that i've",
      "start": 206.879,
      "duration": 3.761
    },
    {
      "text": "had i have a closet full of a few of",
      "start": 208.72,
      "duration": 3.36
    },
    {
      "text": "them i have a garage full",
      "start": 210.64,
      "duration": 2.72
    },
    {
      "text": "of a bunch of them because i've tried",
      "start": 212.08,
      "duration": 3.36
    },
    {
      "text": "every juicer out there and",
      "start": 213.36,
      "duration": 4.56
    },
    {
      "text": "they don't pay for themselves and that's",
      "start": 215.44,
      "duration": 4.56
    },
    {
      "text": "what's crazy it's like i want a juicer",
      "start": 217.92,
      "duration": 2.879
    },
    {
      "text": "to actually",
      "start": 220.0,
      "duration": 3.68
    },
    {
      "text": "you know pay for itself to work for me",
      "start": 220.799,
      "duration": 4.241
    },
    {
      "text": "you know to work for me",
      "start": 223.68,
      "duration": 4.32
    },
    {
      "text": "and this one does it's crazy so you save",
      "start": 225.04,
      "duration": 3.839
    },
    {
      "text": "all that money",
      "start": 228.0,
      "duration": 2.56
    },
    {
      "text": "because you're squeezing every last drop",
      "start": 228.879,
      "duration": 4.161
    },
    {
      "text": "out of out of the celery",
      "start": 230.56,
      "duration": 4.48
    },
    {
      "text": "and it's a it's a big deal so it's",
      "start": 233.04,
      "duration": 3.36
    },
    {
      "text": "really cool so",
      "start": 235.04,
      "duration": 3.199
    },
    {
      "text": "um i'm gonna make sure you know gonna",
      "start": 236.4,
      "duration": 3.44
    },
    {
      "text": "show show you guys how it works going to",
      "start": 238.239,
      "duration": 2.481
    },
    {
      "text": "run it right now",
      "start": 239.84,
      "duration": 2.479
    },
    {
      "text": "juice a little bit can answer some",
      "start": 240.72,
      "duration": 3.76
    },
    {
      "text": "questions if i can too",
      "start": 242.319,
      "duration": 5.92
    },
    {
      "text": "so this is it right here",
      "start": 244.48,
      "duration": 7.759
    },
    {
      "text": "putting some celery in it as we speak",
      "start": 248.239,
      "duration": 4.0
    },
    {
      "text": "i'm just looking for my little plunger",
      "start": 253.2,
      "duration": 6.48
    },
    {
      "text": "it's uh running some now",
      "start": 256.4,
      "duration": 5.6
    },
    {
      "text": "is that juicer just for celery no it's",
      "start": 259.68,
      "duration": 3.519
    },
    {
      "text": "not angela",
      "start": 262.0,
      "duration": 4.4
    },
    {
      "text": "it's a celery juicer which is amazing",
      "start": 263.199,
      "duration": 5.681
    },
    {
      "text": "but you can juice anything in it because",
      "start": 266.4,
      "duration": 4.4
    },
    {
      "text": "it's not it's a top-notch juicer",
      "start": 268.88,
      "duration": 4.08
    },
    {
      "text": "like like the best in my opinion",
      "start": 270.8,
      "duration": 4.16
    },
    {
      "text": "personal opinion the best",
      "start": 272.96,
      "duration": 4.959
    },
    {
      "text": "so it's so great so i'm running some",
      "start": 274.96,
      "duration": 4.239
    },
    {
      "text": "celery right through it now",
      "start": 277.919,
      "duration": 2.961
    },
    {
      "text": "i gotta show you guys like the",
      "start": 279.199,
      "duration": 4.0
    },
    {
      "text": "difference with the pulp like what that",
      "start": 280.88,
      "duration": 5.599
    },
    {
      "text": "is how incredible that is hello from",
      "start": 283.199,
      "duration": 4.321
    },
    {
      "text": "ontario so",
      "start": 286.479,
      "duration": 5.521
    },
    {
      "text": "cool so if anybody just got on here now",
      "start": 287.52,
      "duration": 7.44
    },
    {
      "text": "um well that's a good question dr sebby",
      "start": 292.0,
      "duration": 5.759
    },
    {
      "text": "said celery was bad a hybrid thoughts",
      "start": 294.96,
      "duration": 5.12
    },
    {
      "text": "well first of all dr sebby was still",
      "start": 297.759,
      "duration": 3.121
    },
    {
      "text": "here",
      "start": 300.08,
      "duration": 3.04
    },
    {
      "text": "because i know he passed away if he was",
      "start": 300.88,
      "duration": 4.48
    },
    {
      "text": "still here and he saw what happened with",
      "start": 303.12,
      "duration": 3.84
    },
    {
      "text": "the celery juice movement",
      "start": 305.36,
      "duration": 3.839
    },
    {
      "text": "and he saw millions of people healing",
      "start": 306.96,
      "duration": 3.679
    },
    {
      "text": "and he saw tens of",
      "start": 309.199,
      "duration": 3.28
    },
    {
      "text": "thousands of healing stories people",
      "start": 310.639,
      "duration": 3.361
    },
    {
      "text": "getting out of wheelchairs",
      "start": 312.479,
      "duration": 3.841
    },
    {
      "text": "people getting their lives back acid",
      "start": 314.0,
      "duration": 4.0
    },
    {
      "text": "reflux going away",
      "start": 316.32,
      "duration": 4.8
    },
    {
      "text": "migraines going away difficult",
      "start": 318.0,
      "duration": 4.88
    },
    {
      "text": "menstruations going away",
      "start": 321.12,
      "duration": 3.919
    },
    {
      "text": "if he saw everything happening from",
      "start": 322.88,
      "duration": 3.36
    },
    {
      "text": "celery juice",
      "start": 325.039,
      "duration": 3.761
    },
    {
      "text": "i think he would change his mind because",
      "start": 326.24,
      "duration": 4.48
    },
    {
      "text": "i know he was theorizing because that's",
      "start": 328.8,
      "duration": 3.2
    },
    {
      "text": "what these guys do because there's no",
      "start": 330.72,
      "duration": 3.199
    },
    {
      "text": "there's no science that would state that",
      "start": 332.0,
      "duration": 3.12
    },
    {
      "text": "celery is bad",
      "start": 333.919,
      "duration": 4.081
    },
    {
      "text": "so he was theorizing that it was bad and",
      "start": 335.12,
      "duration": 5.6
    },
    {
      "text": "if he was alive today dr sebby",
      "start": 338.0,
      "duration": 5.12
    },
    {
      "text": "he would actually probably be bowing",
      "start": 340.72,
      "duration": 4.24
    },
    {
      "text": "down to celery juice because his",
      "start": 343.12,
      "duration": 2.96
    },
    {
      "text": "patients",
      "start": 344.96,
      "duration": 2.88
    },
    {
      "text": "would be coming in talking about how",
      "start": 346.08,
      "duration": 3.119
    },
    {
      "text": "it's saving their lives",
      "start": 347.84,
      "duration": 2.96
    },
    {
      "text": "like some of the other doctors out there",
      "start": 349.199,
      "duration": 3.84
    },
    {
      "text": "and stuff so that's how i kind of",
      "start": 350.8,
      "duration": 6.0
    },
    {
      "text": "look at it in that way plus when dr",
      "start": 353.039,
      "duration": 6.16
    },
    {
      "text": "sebby was here i was still here too i've",
      "start": 356.8,
      "duration": 4.88
    },
    {
      "text": "been doing this for 35 years",
      "start": 359.199,
      "duration": 5.761
    },
    {
      "text": "and and",
      "start": 361.68,
      "duration": 6.32
    },
    {
      "text": "i was already getting my people better",
      "start": 364.96,
      "duration": 6.4
    },
    {
      "text": "by the truckloads over the decades and",
      "start": 368.0,
      "duration": 5.36
    },
    {
      "text": "um and they were getting their lives",
      "start": 371.36,
      "duration": 3.52
    },
    {
      "text": "back from celery juice while",
      "start": 373.36,
      "duration": 3.279
    },
    {
      "text": "while he was telling people don't drink",
      "start": 374.88,
      "duration": 3.439
    },
    {
      "text": "it it's just really it just it's",
      "start": 376.639,
      "duration": 2.961
    },
    {
      "text": "unbelievable really",
      "start": 378.319,
      "duration": 4.16
    },
    {
      "text": "when you think about it so celery juice",
      "start": 379.6,
      "duration": 3.2
    },
    {
      "text": "has",
      "start": 382.479,
      "duration": 3.681
    },
    {
      "text": "shaped and changed chronic illness today",
      "start": 382.8,
      "duration": 5.2
    },
    {
      "text": "and when you think about how powerful",
      "start": 386.16,
      "duration": 4.319
    },
    {
      "text": "that is and how amazing that is it's",
      "start": 388.0,
      "duration": 5.28
    },
    {
      "text": "actually breathtaking like the results",
      "start": 390.479,
      "duration": 3.441
    },
    {
      "text": "so",
      "start": 393.28,
      "duration": 1.84
    },
    {
      "text": "[Music]",
      "start": 393.92,
      "duration": 3.92
    },
    {
      "text": "um i know you can't see it too easy",
      "start": 395.12,
      "duration": 4.079
    },
    {
      "text": "right you probably can't see it easy",
      "start": 397.84,
      "duration": 2.479
    },
    {
      "text": "i'll show you",
      "start": 399.199,
      "duration": 2.961
    },
    {
      "text": "i know someone's saying move camera down",
      "start": 400.319,
      "duration": 3.761
    },
    {
      "text": "i know it's difficult to get a good shot",
      "start": 402.16,
      "duration": 4.319
    },
    {
      "text": "today",
      "start": 404.08,
      "duration": 2.399
    },
    {
      "text": "so this is the i just saw a question why",
      "start": 407.44,
      "duration": 4.24
    },
    {
      "text": "do i feel like this is the best juicer",
      "start": 409.759,
      "duration": 3.28
    },
    {
      "text": "well",
      "start": 411.68,
      "duration": 3.84
    },
    {
      "text": "what it does is it's got a device on it",
      "start": 413.039,
      "duration": 3.6
    },
    {
      "text": "right",
      "start": 415.52,
      "duration": 4.16
    },
    {
      "text": "that squeezes all the juice out of",
      "start": 416.639,
      "duration": 3.601
    },
    {
      "text": "celery",
      "start": 419.68,
      "duration": 2.4
    },
    {
      "text": "i can't find a juicer on the market",
      "start": 420.24,
      "duration": 3.04
    },
    {
      "text": "that's ever done that",
      "start": 422.08,
      "duration": 4.48
    },
    {
      "text": "i've purchased them all so when i",
      "start": 423.28,
      "duration": 4.24
    },
    {
      "text": "purchased this",
      "start": 426.56,
      "duration": 4.639
    },
    {
      "text": "this one it was always the best juicer",
      "start": 427.52,
      "duration": 5.519
    },
    {
      "text": "company anyway but when they put the",
      "start": 431.199,
      "duration": 4.881
    },
    {
      "text": "device on it to make it just for celery",
      "start": 433.039,
      "duration": 5.361
    },
    {
      "text": "to get really squeeze that celery juice",
      "start": 436.08,
      "duration": 4.0
    },
    {
      "text": "out it changed everything",
      "start": 438.4,
      "duration": 3.6
    },
    {
      "text": "it was like okay well this is a miracle",
      "start": 440.08,
      "duration": 4.72
    },
    {
      "text": "because i'm saving a ton of money each",
      "start": 442.0,
      "duration": 3.919
    },
    {
      "text": "year",
      "start": 444.8,
      "duration": 3.28
    },
    {
      "text": "and that's that's a big deal celery",
      "start": 445.919,
      "duration": 4.081
    },
    {
      "text": "juice cured me from my debilitating",
      "start": 448.08,
      "duration": 4.16
    },
    {
      "text": "migraines michelle marie said",
      "start": 450.0,
      "duration": 4.96
    },
    {
      "text": "right i wonder what dr sebby would say",
      "start": 452.24,
      "duration": 4.64
    },
    {
      "text": "about that one",
      "start": 454.96,
      "duration": 4.16
    },
    {
      "text": "because he doesn't he didn't like celery",
      "start": 456.88,
      "duration": 3.84
    },
    {
      "text": "and it cured you of your debilitating",
      "start": 459.12,
      "duration": 2.56
    },
    {
      "text": "migraines",
      "start": 460.72,
      "duration": 2.96
    },
    {
      "text": "that's what i'm talking about that's",
      "start": 461.68,
      "duration": 3.519
    },
    {
      "text": "what i'm talking about that's",
      "start": 463.68,
      "duration": 3.6
    },
    {
      "text": "such a big deal that means everything",
      "start": 465.199,
      "duration": 4.321
    },
    {
      "text": "honestly that means everything",
      "start": 467.28,
      "duration": 5.84
    },
    {
      "text": "so you'll see pulp coming out right now",
      "start": 469.52,
      "duration": 5.2
    },
    {
      "text": "and this isn't just for celery you could",
      "start": 473.12,
      "duration": 2.88
    },
    {
      "text": "use anything in this juicer that's",
      "start": 474.72,
      "duration": 2.08
    },
    {
      "text": "what's incredible",
      "start": 476.0,
      "duration": 2.72
    },
    {
      "text": "that's what i love so i'm juicing a",
      "start": 476.8,
      "duration": 3.519
    },
    {
      "text": "little bit more i'm gonna put a couple",
      "start": 478.72,
      "duration": 3.52
    },
    {
      "text": "more pieces in right here",
      "start": 480.319,
      "duration": 5.231
    },
    {
      "text": "[Music]",
      "start": 482.24,
      "duration": 3.31
    },
    {
      "text": "[Applause]",
      "start": 486.22,
      "duration": 3.179
    },
    {
      "text": "so",
      "start": 490.84,
      "duration": 3.0
    },
    {
      "text": "i see it my husband learned in his",
      "start": 495.84,
      "duration": 3.759
    },
    {
      "text": "toxicology class celery",
      "start": 498.0,
      "duration": 4.479
    },
    {
      "text": "is celery is full filled with nitrates",
      "start": 499.599,
      "duration": 4.88
    },
    {
      "text": "not correct",
      "start": 502.479,
      "duration": 5.44
    },
    {
      "text": "sorry it's not correct i wrote a celery",
      "start": 504.479,
      "duration": 4.961
    },
    {
      "text": "juice book",
      "start": 507.919,
      "duration": 3.68
    },
    {
      "text": "all about that and i talked about that",
      "start": 509.44,
      "duration": 3.92
    },
    {
      "text": "in here everything about it and where",
      "start": 511.599,
      "duration": 2.56
    },
    {
      "text": "the confusion",
      "start": 513.36,
      "duration": 3.919
    },
    {
      "text": "fusion lies um that's in celery",
      "start": 514.159,
      "duration": 6.24
    },
    {
      "text": "powder for preserving things",
      "start": 517.279,
      "duration": 6.721
    },
    {
      "text": "and it they add nitrate to it so that's",
      "start": 520.399,
      "duration": 7.361
    },
    {
      "text": "only for the preserving factories for",
      "start": 524.0,
      "duration": 5.04
    },
    {
      "text": "preserving food",
      "start": 527.76,
      "duration": 3.92
    },
    {
      "text": "they they actually take celery powder",
      "start": 529.04,
      "duration": 4.08
    },
    {
      "text": "and they add nitrate",
      "start": 531.68,
      "duration": 5.279
    },
    {
      "text": "to it to try to preserve fish",
      "start": 533.12,
      "duration": 7.279
    },
    {
      "text": "so that's misinformation",
      "start": 536.959,
      "duration": 3.44
    },
    {
      "text": "i've i've actually seen",
      "start": 540.48,
      "duration": 6.56
    },
    {
      "text": "everything about that and then some",
      "start": 543.839,
      "duration": 7.601
    },
    {
      "text": "so i dispute it with facts",
      "start": 547.04,
      "duration": 5.84
    },
    {
      "text": "so here we go i got to show you guys",
      "start": 551.44,
      "duration": 3.2
    },
    {
      "text": "this this is incredible okay",
      "start": 552.88,
      "duration": 3.84
    },
    {
      "text": "this is just absolutely incredible check",
      "start": 554.64,
      "duration": 3.52
    },
    {
      "text": "this out right",
      "start": 556.72,
      "duration": 4.4
    },
    {
      "text": "seriously this blows my mind every time",
      "start": 558.16,
      "duration": 5.119
    },
    {
      "text": "if you guys ever juiced before",
      "start": 561.12,
      "duration": 4.159
    },
    {
      "text": "or juiced with other juicers you're",
      "start": 563.279,
      "duration": 3.841
    },
    {
      "text": "gonna know what this means right here",
      "start": 565.279,
      "duration": 4.401
    },
    {
      "text": "this is this is mind-blowing right okay",
      "start": 567.12,
      "duration": 4.159
    },
    {
      "text": "so",
      "start": 569.68,
      "duration": 5.12
    },
    {
      "text": "all right that's my celery juice okay",
      "start": 571.279,
      "duration": 6.56
    },
    {
      "text": "that's over 32 ounces all right that's",
      "start": 574.8,
      "duration": 4.719
    },
    {
      "text": "my celery juice right there",
      "start": 577.839,
      "duration": 4.321
    },
    {
      "text": "okay let's check this out okay that's",
      "start": 579.519,
      "duration": 4.88
    },
    {
      "text": "that",
      "start": 582.16,
      "duration": 4.56
    },
    {
      "text": "all right",
      "start": 584.399,
      "duration": 2.321
    },
    {
      "text": "look at this on my fingertips",
      "start": 587.44,
      "duration": 4.959
    },
    {
      "text": "do you see what i'm saying right here do",
      "start": 590.72,
      "duration": 3.119
    },
    {
      "text": "you see what i'm holding",
      "start": 592.399,
      "duration": 5.841
    },
    {
      "text": "and you ready it's a dry piece of rope",
      "start": 593.839,
      "duration": 8.401
    },
    {
      "text": "look at this it's a dry",
      "start": 598.24,
      "duration": 6.719
    },
    {
      "text": "piece of rope with no juice in it but",
      "start": 602.24,
      "duration": 3.92
    },
    {
      "text": "look at how tiny it is",
      "start": 604.959,
      "duration": 3.201
    },
    {
      "text": "look at this this little dry piece of",
      "start": 606.16,
      "duration": 3.52
    },
    {
      "text": "rope",
      "start": 608.16,
      "duration": 4.0
    },
    {
      "text": "that's the difference right there what",
      "start": 609.68,
      "duration": 4.88
    },
    {
      "text": "this is saving me money wise",
      "start": 612.16,
      "duration": 4.96
    },
    {
      "text": "each year because i juice like 60 ounces",
      "start": 614.56,
      "duration": 4.719
    },
    {
      "text": "40 ounces 100 ounces a day whatever i",
      "start": 617.12,
      "duration": 3.52
    },
    {
      "text": "just juice juice it",
      "start": 619.279,
      "duration": 3.761
    },
    {
      "text": "and and i know i know other people would",
      "start": 620.64,
      "duration": 3.68
    },
    {
      "text": "do the same",
      "start": 623.04,
      "duration": 4.32
    },
    {
      "text": "what this is saving us is unbelievable",
      "start": 624.32,
      "duration": 4.8
    },
    {
      "text": "this is dehydrated",
      "start": 627.36,
      "duration": 3.84
    },
    {
      "text": "it's there's no juice in it and it's",
      "start": 629.12,
      "duration": 3.36
    },
    {
      "text": "this tiny",
      "start": 631.2,
      "duration": 4.4
    },
    {
      "text": "little pulp look at that i'm not kidding",
      "start": 632.48,
      "duration": 3.919
    },
    {
      "text": "like",
      "start": 635.6,
      "duration": 4.08
    },
    {
      "text": "that's mind-blowing for all that",
      "start": 636.399,
      "duration": 5.041
    },
    {
      "text": "guess what there's no juicer on the",
      "start": 639.68,
      "duration": 3.279
    },
    {
      "text": "market that can do that i don't care",
      "start": 641.44,
      "duration": 3.44
    },
    {
      "text": "who's what how i've tried them all",
      "start": 642.959,
      "duration": 3.521
    },
    {
      "text": "and i love how they talk a good game",
      "start": 644.88,
      "duration": 3.04
    },
    {
      "text": "because they want to be like they don't",
      "start": 646.48,
      "duration": 2.32
    },
    {
      "text": "want",
      "start": 647.92,
      "duration": 3.359
    },
    {
      "text": "they don't want a mega you know actually",
      "start": 648.8,
      "duration": 3.2
    },
    {
      "text": "having such",
      "start": 651.279,
      "duration": 2.721
    },
    {
      "text": "an amazing amazing product because it's",
      "start": 652.0,
      "duration": 3.519
    },
    {
      "text": "competition out there so they'll talk a",
      "start": 654.0,
      "duration": 2.0
    },
    {
      "text": "good game",
      "start": 655.519,
      "duration": 3.201
    },
    {
      "text": "our juicer does just as good as a job no",
      "start": 656.0,
      "duration": 3.44
    },
    {
      "text": "it doesn't",
      "start": 658.72,
      "duration": 5.64
    },
    {
      "text": "no it doesn't this is the mm-900",
      "start": 659.44,
      "duration": 7.6
    },
    {
      "text": "hds celery juicer",
      "start": 664.36,
      "duration": 5.479
    },
    {
      "text": "i'm just telling you i i until this till",
      "start": 667.04,
      "duration": 3.52
    },
    {
      "text": "this day",
      "start": 669.839,
      "duration": 3.521
    },
    {
      "text": "this is this is unbelievable i keep on",
      "start": 670.56,
      "duration": 4.64
    },
    {
      "text": "thinking it's like a joke or something",
      "start": 673.36,
      "duration": 4.56
    },
    {
      "text": "i have i have the container and it's",
      "start": 675.2,
      "duration": 4.16
    },
    {
      "text": "this little piece",
      "start": 677.92,
      "duration": 4.56
    },
    {
      "text": "of dried rope with nothing in it",
      "start": 679.36,
      "duration": 4.719
    },
    {
      "text": "this tiny little piece of dried rope",
      "start": 682.48,
      "duration": 3.039
    },
    {
      "text": "right here",
      "start": 684.079,
      "duration": 5.2
    },
    {
      "text": "for this i mean honestly i'm gonna pour",
      "start": 685.519,
      "duration": 5.44
    },
    {
      "text": "it in and everything you guys",
      "start": 689.279,
      "duration": 3.68
    },
    {
      "text": "um celery has cured me of debilitating",
      "start": 690.959,
      "duration": 3.44
    },
    {
      "text": "migraines too",
      "start": 692.959,
      "duration": 4.0
    },
    {
      "text": "so cynthia says celery has cured you of",
      "start": 694.399,
      "duration": 4.161
    },
    {
      "text": "debilitating migraines too",
      "start": 696.959,
      "duration": 4.961
    },
    {
      "text": "oh my god amazing isn't that worth it",
      "start": 698.56,
      "duration": 5.44
    },
    {
      "text": "isn't that worth it how can i wash",
      "start": 701.92,
      "duration": 4.24
    },
    {
      "text": "non-organic celery you know what you",
      "start": 704.0,
      "duration": 3.44
    },
    {
      "text": "know what i do you guys",
      "start": 706.16,
      "duration": 3.919
    },
    {
      "text": "i i juice non-organic celery a lot if i",
      "start": 707.44,
      "duration": 3.92
    },
    {
      "text": "can't get the organic stuff",
      "start": 710.079,
      "duration": 2.801
    },
    {
      "text": "i'm always getting the non-organic for",
      "start": 711.36,
      "duration": 4.24
    },
    {
      "text": "celery always um",
      "start": 712.88,
      "duration": 5.44
    },
    {
      "text": "what i do is i wash right in here i make",
      "start": 715.6,
      "duration": 4.56
    },
    {
      "text": "sure my thumb goes in here",
      "start": 718.32,
      "duration": 4.079
    },
    {
      "text": "when i'm washing it and i actually do",
      "start": 720.16,
      "duration": 3.359
    },
    {
      "text": "this where i'm",
      "start": 722.399,
      "duration": 3.921
    },
    {
      "text": "i'm actually washing kind of scrubbing",
      "start": 723.519,
      "duration": 3.841
    },
    {
      "text": "this here",
      "start": 726.32,
      "duration": 3.44
    },
    {
      "text": "and i use a little tiny bit of natural",
      "start": 727.36,
      "duration": 3.44
    },
    {
      "text": "dish soap",
      "start": 729.76,
      "duration": 3.28
    },
    {
      "text": "in the bowl of water and i kind of rub",
      "start": 730.8,
      "duration": 4.08
    },
    {
      "text": "the sticks that's that's what you do",
      "start": 733.04,
      "duration": 3.919
    },
    {
      "text": "that's what i do i do it every other day",
      "start": 734.88,
      "duration": 3.199
    },
    {
      "text": "when i can't get it",
      "start": 736.959,
      "duration": 4.721
    },
    {
      "text": "um it's amazing my pulp is always full",
      "start": 738.079,
      "duration": 4.32
    },
    {
      "text": "of juice",
      "start": 741.68,
      "duration": 2.88
    },
    {
      "text": "deanna deanna this is really incredible",
      "start": 742.399,
      "duration": 3.201
    },
    {
      "text": "really",
      "start": 744.56,
      "duration": 4.079
    },
    {
      "text": "um jillian gray says what do you set",
      "start": 745.6,
      "duration": 5.679
    },
    {
      "text": "it on to get the dryness i have an omega",
      "start": 748.639,
      "duration": 3.921
    },
    {
      "text": "but it still comes",
      "start": 751.279,
      "duration": 3.601
    },
    {
      "text": "out quite wet i put the pulp through",
      "start": 752.56,
      "duration": 3.36
    },
    {
      "text": "again that's",
      "start": 754.88,
      "duration": 3.04
    },
    {
      "text": "well doing you have it omega but omega",
      "start": 755.92,
      "duration": 3.76
    },
    {
      "text": "has a bunch of juicers in and that's not",
      "start": 757.92,
      "duration": 2.88
    },
    {
      "text": "this one",
      "start": 759.68,
      "duration": 5.0
    },
    {
      "text": "this is the mm-900",
      "start": 760.8,
      "duration": 7.36
    },
    {
      "text": "hds celery juicer from omega",
      "start": 764.68,
      "duration": 5.64
    },
    {
      "text": "and it uses everything else too this is",
      "start": 768.16,
      "duration": 3.84
    },
    {
      "text": "an entirely different thing they did",
      "start": 770.32,
      "duration": 4.88
    },
    {
      "text": "this because you know they want it to",
      "start": 772.0,
      "duration": 3.519
    },
    {
      "text": "just",
      "start": 775.2,
      "duration": 2.56
    },
    {
      "text": "change people's lives with this i mean",
      "start": 775.519,
      "duration": 3.921
    },
    {
      "text": "no dry to the bone",
      "start": 777.76,
      "duration": 3.36
    },
    {
      "text": "i can't even tell you how i mean this is",
      "start": 779.44,
      "duration": 3.28
    },
    {
      "text": "this is unbelievable and it's only a",
      "start": 781.12,
      "duration": 2.56
    },
    {
      "text": "tiny bit",
      "start": 782.72,
      "duration": 3.76
    },
    {
      "text": "look at that tiny bit for this whole",
      "start": 783.68,
      "duration": 3.76
    },
    {
      "text": "thing right here so",
      "start": 786.48,
      "duration": 3.84
    },
    {
      "text": "um i'm going to actually pour it in i",
      "start": 787.44,
      "duration": 4.16
    },
    {
      "text": "mean honestly",
      "start": 790.32,
      "duration": 4.48
    },
    {
      "text": "every time i do it every morning",
      "start": 791.6,
      "duration": 5.919
    },
    {
      "text": "you're mind blown i mean seriously just",
      "start": 794.8,
      "duration": 4.479
    },
    {
      "text": "mind blown i use a strainer you gotta",
      "start": 797.519,
      "duration": 2.481
    },
    {
      "text": "strain",
      "start": 799.279,
      "duration": 2.481
    },
    {
      "text": "even though you just juiced it you",
      "start": 800.0,
      "duration": 3.2
    },
    {
      "text": "should still strain it",
      "start": 801.76,
      "duration": 4.48
    },
    {
      "text": "should still strain it that that's the",
      "start": 803.2,
      "duration": 6.16
    },
    {
      "text": "best way to do it there",
      "start": 806.24,
      "duration": 3.12
    },
    {
      "text": "it's still the best way to do glad it",
      "start": 810.72,
      "duration": 4.88
    },
    {
      "text": "guys are with me today i'm excited about",
      "start": 814.0,
      "duration": 3.04
    },
    {
      "text": "this so that's it",
      "start": 815.6,
      "duration": 4.56
    },
    {
      "text": "there okay",
      "start": 817.04,
      "duration": 3.12
    },
    {
      "text": "look at that okay incredible and i got",
      "start": 820.639,
      "duration": 3.841
    },
    {
      "text": "this dried out",
      "start": 823.279,
      "duration": 3.041
    },
    {
      "text": "little tiny bit of rope right here now",
      "start": 824.48,
      "duration": 3.12
    },
    {
      "text": "the difference is with that",
      "start": 826.32,
      "duration": 5.44
    },
    {
      "text": "is it can save me like",
      "start": 827.6,
      "duration": 5.599
    },
    {
      "text": "it's in the thousands at the end of the",
      "start": 831.76,
      "duration": 4.8
    },
    {
      "text": "year i buy so many cases of celery",
      "start": 833.199,
      "duration": 6.481
    },
    {
      "text": "and it cut the cost in half",
      "start": 836.56,
      "duration": 5.04
    },
    {
      "text": "just boom this juicer paid for itself",
      "start": 839.68,
      "duration": 3.2
    },
    {
      "text": "over and over",
      "start": 841.6,
      "duration": 2.56
    },
    {
      "text": "and over and over again and guess what",
      "start": 842.88,
      "duration": 3.12
    },
    {
      "text": "this isn't a 700 juicer",
      "start": 844.16,
      "duration": 4.08
    },
    {
      "text": "this isn't a thousand dollar juicer this",
      "start": 846.0,
      "duration": 3.199
    },
    {
      "text": "isn't like",
      "start": 848.24,
      "duration": 4.88
    },
    {
      "text": "a 1500 juicer or a 600 juicer",
      "start": 849.199,
      "duration": 6.64
    },
    {
      "text": "it's on sale it's 200 and something",
      "start": 853.12,
      "duration": 3.279
    },
    {
      "text": "dollars",
      "start": 855.839,
      "duration": 2.881
    },
    {
      "text": "it's it's it's black friday on top of it",
      "start": 856.399,
      "duration": 3.281
    },
    {
      "text": "it just doesn't",
      "start": 858.72,
      "duration": 2.88
    },
    {
      "text": "it just doesn't get any better than that",
      "start": 859.68,
      "duration": 3.76
    },
    {
      "text": "um",
      "start": 861.6,
      "duration": 5.039
    },
    {
      "text": "so uh natalie celery has fast-tracked my",
      "start": 863.44,
      "duration": 4.0
    },
    {
      "text": "healing from",
      "start": 866.639,
      "duration": 4.081
    },
    {
      "text": "graves disease thank you anthony natalie",
      "start": 867.44,
      "duration": 4.959
    },
    {
      "text": "thank you for doing it because when you",
      "start": 870.72,
      "duration": 2.32
    },
    {
      "text": "do it",
      "start": 872.399,
      "duration": 3.12
    },
    {
      "text": "it first of all you know when you",
      "start": 873.04,
      "duration": 4.239
    },
    {
      "text": "actually take that plunge and you're",
      "start": 875.519,
      "duration": 3.12
    },
    {
      "text": "doing your celery juice and you're",
      "start": 877.279,
      "duration": 3.201
    },
    {
      "text": "working on your healing process",
      "start": 878.639,
      "duration": 3.681
    },
    {
      "text": "you become a beacon of light for",
      "start": 880.48,
      "duration": 3.12
    },
    {
      "text": "everybody else",
      "start": 882.32,
      "duration": 4.959
    },
    {
      "text": "and and that's that's powerful powerful",
      "start": 883.6,
      "duration": 5.2
    },
    {
      "text": "because someone else is suffering and",
      "start": 887.279,
      "duration": 3.12
    },
    {
      "text": "struggling and boom",
      "start": 888.8,
      "duration": 3.68
    },
    {
      "text": "your word and you're you're you're doing",
      "start": 890.399,
      "duration": 3.921
    },
    {
      "text": "your work and all of a sudden",
      "start": 892.48,
      "duration": 4.0
    },
    {
      "text": "someone sees or hears about it and boom",
      "start": 894.32,
      "duration": 3.92
    },
    {
      "text": "you just you just change somebody's like",
      "start": 896.48,
      "duration": 4.24
    },
    {
      "text": "possibly save somebody's life robin",
      "start": 898.24,
      "duration": 4.56
    },
    {
      "text": "young buyer celery juice cleared up all",
      "start": 900.72,
      "duration": 2.559
    },
    {
      "text": "skin",
      "start": 902.8,
      "duration": 2.8
    },
    {
      "text": "issues robin that's incredible because",
      "start": 903.279,
      "duration": 4.56
    },
    {
      "text": "skin is just really brutal brutal for a",
      "start": 905.6,
      "duration": 3.52
    },
    {
      "text": "lot of people and they're really",
      "start": 907.839,
      "duration": 2.721
    },
    {
      "text": "difficult",
      "start": 909.12,
      "duration": 3.279
    },
    {
      "text": "and people really struggle and that",
      "start": 910.56,
      "duration": 3.2
    },
    {
      "text": "that's the best news i've heard",
      "start": 912.399,
      "duration": 3.12
    },
    {
      "text": "really is such good news i'm so happy to",
      "start": 913.76,
      "duration": 3.36
    },
    {
      "text": "hear that",
      "start": 915.519,
      "duration": 4.721
    },
    {
      "text": "so you're really happy to hear that um",
      "start": 917.12,
      "duration": 5.279
    },
    {
      "text": "rita asked does celery have sodium in it",
      "start": 920.24,
      "duration": 2.8
    },
    {
      "text": "yeah it has",
      "start": 922.399,
      "duration": 3.041
    },
    {
      "text": "natural sodium cluster salts a subgroup",
      "start": 923.04,
      "duration": 3.52
    },
    {
      "text": "of sodium",
      "start": 925.44,
      "duration": 3.12
    },
    {
      "text": "that's your medicine that's different",
      "start": 926.56,
      "duration": 3.199
    },
    {
      "text": "than salt",
      "start": 928.56,
      "duration": 3.68
    },
    {
      "text": "that's your medicine it's just",
      "start": 929.759,
      "duration": 3.52
    },
    {
      "text": "incredible",
      "start": 932.24,
      "duration": 3.599
    },
    {
      "text": "but you know yeah michelle aren't aren't",
      "start": 933.279,
      "duration": 4.24
    },
    {
      "text": "skin issues really bad they're so bad",
      "start": 935.839,
      "duration": 3.601
    },
    {
      "text": "people's skin issues are just terrible",
      "start": 937.519,
      "duration": 2.981
    },
    {
      "text": "terrible",
      "start": 939.44,
      "duration": 2.24
    },
    {
      "text": "[Music]",
      "start": 940.5,
      "duration": 3.98
    },
    {
      "text": "so celery juice is one of these things",
      "start": 941.68,
      "duration": 3.12
    },
    {
      "text": "that",
      "start": 944.48,
      "duration": 2.4
    },
    {
      "text": "has benefits beyond what research and",
      "start": 944.8,
      "duration": 3.2
    },
    {
      "text": "science knows first of all they didn't",
      "start": 946.88,
      "duration": 2.399
    },
    {
      "text": "know it had any benefits",
      "start": 948.0,
      "duration": 4.48
    },
    {
      "text": "medical medium information put out",
      "start": 949.279,
      "duration": 5.441
    },
    {
      "text": "information on celery juice okay there",
      "start": 952.48,
      "duration": 4.64
    },
    {
      "text": "was no information on celery juice",
      "start": 954.72,
      "duration": 4.88
    },
    {
      "text": "that existed okay it was all medical",
      "start": 957.12,
      "duration": 3.68
    },
    {
      "text": "medium information",
      "start": 959.6,
      "duration": 2.64
    },
    {
      "text": "and now people are toting it out there",
      "start": 960.8,
      "duration": 2.719
    },
    {
      "text": "everywhere they're saying it does this",
      "start": 962.24,
      "duration": 2.719
    },
    {
      "text": "that does that it does this they don't",
      "start": 963.519,
      "duration": 3.041
    },
    {
      "text": "cite back to medical medium but they'll",
      "start": 964.959,
      "duration": 3.041
    },
    {
      "text": "say it does this this this",
      "start": 966.56,
      "duration": 2.719
    },
    {
      "text": "lower blood pressure do this all the",
      "start": 968.0,
      "duration": 3.12
    },
    {
      "text": "stuff and they don't cite anything back",
      "start": 969.279,
      "duration": 3.521
    },
    {
      "text": "to medical medium they act like",
      "start": 971.12,
      "duration": 3.6
    },
    {
      "text": "there's been real research and studies",
      "start": 972.8,
      "duration": 3.2
    },
    {
      "text": "on it there isn't",
      "start": 974.72,
      "duration": 3.76
    },
    {
      "text": "there hasn't there hasn't been any",
      "start": 976.0,
      "duration": 3.759
    },
    {
      "text": "research",
      "start": 978.48,
      "duration": 4.159
    },
    {
      "text": "and studies on celery juice but guess",
      "start": 979.759,
      "duration": 3.76
    },
    {
      "text": "what",
      "start": 982.639,
      "duration": 2.801
    },
    {
      "text": "millions are healing and reversing",
      "start": 983.519,
      "duration": 4.801
    },
    {
      "text": "disease and symptoms and conditions so",
      "start": 985.44,
      "duration": 4.56
    },
    {
      "text": "let's talk about benefits a little bit",
      "start": 988.32,
      "duration": 3.199
    },
    {
      "text": "that's exciting right there so i got my",
      "start": 990.0,
      "duration": 3.279
    },
    {
      "text": "celery juice just juiced it right here",
      "start": 991.519,
      "duration": 3.601
    },
    {
      "text": "and if you guys just got on here",
      "start": 993.279,
      "duration": 4.721
    },
    {
      "text": "i'm just gonna show you this okay if you",
      "start": 995.12,
      "duration": 4.0
    },
    {
      "text": "just got on",
      "start": 998.0,
      "duration": 4.639
    },
    {
      "text": "um because",
      "start": 999.12,
      "duration": 7.04
    },
    {
      "text": "i just juiced over 32 ounces of celery",
      "start": 1002.639,
      "duration": 4.961
    },
    {
      "text": "juice okay",
      "start": 1006.16,
      "duration": 6.08
    },
    {
      "text": "that's what i did and in this container",
      "start": 1007.6,
      "duration": 7.44
    },
    {
      "text": "it's it's a joke how much how how little",
      "start": 1012.24,
      "duration": 3.76
    },
    {
      "text": "is in here",
      "start": 1015.04,
      "duration": 3.28
    },
    {
      "text": "in this container right here there's",
      "start": 1016.0,
      "duration": 4.48
    },
    {
      "text": "this little bit in the corner",
      "start": 1018.32,
      "duration": 5.999
    },
    {
      "text": "look and",
      "start": 1020.48,
      "duration": 7.28
    },
    {
      "text": "it's dry to the bone that's it",
      "start": 1024.319,
      "duration": 6.961
    },
    {
      "text": "um i washed all this celery and i don't",
      "start": 1027.76,
      "duration": 5.039
    },
    {
      "text": "need to juice it",
      "start": 1031.28,
      "duration": 3.36
    },
    {
      "text": "i'm going to juice it later because i'm",
      "start": 1032.799,
      "duration": 4.0
    },
    {
      "text": "still going to do some lives",
      "start": 1034.64,
      "duration": 5.439
    },
    {
      "text": "but is unbelievable so it's just great",
      "start": 1036.799,
      "duration": 4.321
    },
    {
      "text": "it's great so i want to talk about",
      "start": 1040.079,
      "duration": 2.24
    },
    {
      "text": "benefits of celery",
      "start": 1041.12,
      "duration": 4.319
    },
    {
      "text": "i'm going to grab a celery stick right",
      "start": 1042.319,
      "duration": 3.841
    },
    {
      "text": "here",
      "start": 1045.439,
      "duration": 2.88
    },
    {
      "text": "um just grab this one this is a great",
      "start": 1046.16,
      "duration": 3.519
    },
    {
      "text": "celery stick",
      "start": 1048.319,
      "duration": 3.441
    },
    {
      "text": "so everybody's been asking me to twirl",
      "start": 1049.679,
      "duration": 4.0
    },
    {
      "text": "the celery sticks",
      "start": 1051.76,
      "duration": 3.44
    },
    {
      "text": "like in the celery just video on tick",
      "start": 1053.679,
      "duration": 3.041
    },
    {
      "text": "tock i'm just saying they've always been",
      "start": 1055.2,
      "duration": 2.719
    },
    {
      "text": "there everybody's asking me can you do",
      "start": 1056.72,
      "duration": 2.0
    },
    {
      "text": "it again can you",
      "start": 1057.919,
      "duration": 2.401
    },
    {
      "text": "control it can you twirl it it's pretty",
      "start": 1058.72,
      "duration": 3.6
    },
    {
      "text": "funny but um anyway",
      "start": 1060.32,
      "duration": 3.68
    },
    {
      "text": "so the benefits of celery let's just",
      "start": 1062.32,
      "duration": 3.359
    },
    {
      "text": "talk about about it a little bit there's",
      "start": 1064.0,
      "duration": 3.44
    },
    {
      "text": "a vitamin c",
      "start": 1065.679,
      "duration": 5.12
    },
    {
      "text": "in celery okay a vitamin c and",
      "start": 1067.44,
      "duration": 5.92
    },
    {
      "text": "you can eat the celery sticks but you",
      "start": 1070.799,
      "duration": 4.801
    },
    {
      "text": "don't get enough of all its medicine",
      "start": 1073.36,
      "duration": 5.199
    },
    {
      "text": "it's vitamin c it's sodium cluster salts",
      "start": 1075.6,
      "duration": 4.72
    },
    {
      "text": "and i'll talk about what these things do",
      "start": 1078.559,
      "duration": 5.201
    },
    {
      "text": "okay um it's phytochemical compounds",
      "start": 1080.32,
      "duration": 6.64
    },
    {
      "text": "right it it doesn't you can't get enough",
      "start": 1083.76,
      "duration": 4.72
    },
    {
      "text": "if you eat the sticks",
      "start": 1086.96,
      "duration": 2.959
    },
    {
      "text": "so somebody like well i'm just gonna eat",
      "start": 1088.48,
      "duration": 3.36
    },
    {
      "text": "the sticks and be fine with that",
      "start": 1089.919,
      "duration": 4.241
    },
    {
      "text": "no it's not gonna happen that way you're",
      "start": 1091.84,
      "duration": 3.12
    },
    {
      "text": "not if",
      "start": 1094.16,
      "duration": 2.24
    },
    {
      "text": "you if you chop up a little bit of this",
      "start": 1094.96,
      "duration": 2.88
    },
    {
      "text": "and put it in your tuna salad you're not",
      "start": 1096.4,
      "duration": 2.72
    },
    {
      "text": "going to get anywhere with it if you",
      "start": 1097.84,
      "duration": 2.719
    },
    {
      "text": "have this crudite with this",
      "start": 1099.12,
      "duration": 3.28
    },
    {
      "text": "and you're dipping it in some some ranch",
      "start": 1100.559,
      "duration": 3.36
    },
    {
      "text": "dressing whatever it is",
      "start": 1102.4,
      "duration": 3.279
    },
    {
      "text": "you're not going to get you're not going",
      "start": 1103.919,
      "duration": 3.841
    },
    {
      "text": "to get the benefits if you eat it or",
      "start": 1105.679,
      "duration": 4.321
    },
    {
      "text": "chop it up in your salad you're still",
      "start": 1107.76,
      "duration": 5.84
    },
    {
      "text": "not gonna get the benefits you have to",
      "start": 1110.0,
      "duration": 7.2
    },
    {
      "text": "juice it that's the key you can use and",
      "start": 1113.6,
      "duration": 6.0
    },
    {
      "text": "you can use whatever juicer you have",
      "start": 1117.2,
      "duration": 3.92
    },
    {
      "text": "you can use whatever juicer you have if",
      "start": 1119.6,
      "duration": 3.04
    },
    {
      "text": "you guys got a juicer use it",
      "start": 1121.12,
      "duration": 3.919
    },
    {
      "text": "okay i'm just showing you a place you",
      "start": 1122.64,
      "duration": 3.84
    },
    {
      "text": "can go down the road",
      "start": 1125.039,
      "duration": 3.681
    },
    {
      "text": "with a juicer that can change your life",
      "start": 1126.48,
      "duration": 4.16
    },
    {
      "text": "for money-wise it can save you",
      "start": 1128.72,
      "duration": 4.959
    },
    {
      "text": "so much money all of that and and plus",
      "start": 1130.64,
      "duration": 3.52
    },
    {
      "text": "it's just",
      "start": 1133.679,
      "duration": 2.561
    },
    {
      "text": "it's cold it's a cold pressed juicer",
      "start": 1134.16,
      "duration": 3.44
    },
    {
      "text": "it's a cold pressed juicer which is",
      "start": 1136.24,
      "duration": 3.28
    },
    {
      "text": "amazing on top of it",
      "start": 1137.6,
      "duration": 5.04
    },
    {
      "text": "so it just it doesn't butcher the celery",
      "start": 1139.52,
      "duration": 5.2
    },
    {
      "text": "it doesn't butcher it and heat it up and",
      "start": 1142.64,
      "duration": 3.52
    },
    {
      "text": "butcher it so that's another thing too",
      "start": 1144.72,
      "duration": 2.8
    },
    {
      "text": "but anyway go back to the benefits a",
      "start": 1146.16,
      "duration": 3.04
    },
    {
      "text": "little bit all right",
      "start": 1147.52,
      "duration": 5.36
    },
    {
      "text": "so there's a vitamin c in celery",
      "start": 1149.2,
      "duration": 7.28
    },
    {
      "text": "that does not have to be converted",
      "start": 1152.88,
      "duration": 5.919
    },
    {
      "text": "vitamin c has to be converted by your",
      "start": 1156.48,
      "duration": 4.48
    },
    {
      "text": "liver in order to make it work",
      "start": 1158.799,
      "duration": 4.801
    },
    {
      "text": "in order for it to actually work it has",
      "start": 1160.96,
      "duration": 4.4
    },
    {
      "text": "to be converted",
      "start": 1163.6,
      "duration": 4.319
    },
    {
      "text": "in celery it doesn't have to be that",
      "start": 1165.36,
      "duration": 3.199
    },
    {
      "text": "means",
      "start": 1167.919,
      "duration": 3.281
    },
    {
      "text": "that that vitamin c boom goes straight",
      "start": 1168.559,
      "duration": 4.081
    },
    {
      "text": "to your immune system",
      "start": 1171.2,
      "duration": 5.839
    },
    {
      "text": "instantly it doesn't go around the bend",
      "start": 1172.64,
      "duration": 7.36
    },
    {
      "text": "to finally try to get there it doesn't",
      "start": 1177.039,
      "duration": 3.76
    },
    {
      "text": "have to go",
      "start": 1180.0,
      "duration": 3.6
    },
    {
      "text": "to the middle man which is your liver",
      "start": 1180.799,
      "duration": 3.361
    },
    {
      "text": "see",
      "start": 1183.6,
      "duration": 3.68
    },
    {
      "text": "vitamin c has to go",
      "start": 1184.16,
      "duration": 6.08
    },
    {
      "text": "to your liver any vitamin c in food so",
      "start": 1187.28,
      "duration": 4.0
    },
    {
      "text": "any vitamin c",
      "start": 1190.24,
      "duration": 2.88
    },
    {
      "text": "if you've been taught eat this food",
      "start": 1191.28,
      "duration": 3.92
    },
    {
      "text": "because it's got vitamin c",
      "start": 1193.12,
      "duration": 5.36
    },
    {
      "text": "it has to go to the liver first",
      "start": 1195.2,
      "duration": 6.4
    },
    {
      "text": "get converted and then it can go to your",
      "start": 1198.48,
      "duration": 4.24
    },
    {
      "text": "immune system",
      "start": 1201.6,
      "duration": 3.76
    },
    {
      "text": "well here's the difference right here",
      "start": 1202.72,
      "duration": 3.839
    },
    {
      "text": "right here and you know what you know",
      "start": 1205.36,
      "duration": 3.199
    },
    {
      "text": "why vitamin c is an important thing",
      "start": 1206.559,
      "duration": 4.24
    },
    {
      "text": "right now well everybody's locked in",
      "start": 1208.559,
      "duration": 3.281
    },
    {
      "text": "their homes",
      "start": 1210.799,
      "duration": 3.601
    },
    {
      "text": "everybody's wearing you know outfits to",
      "start": 1211.84,
      "duration": 4.4
    },
    {
      "text": "try to protect themselves",
      "start": 1214.4,
      "duration": 4.159
    },
    {
      "text": "because of what's going down vitamin c",
      "start": 1216.24,
      "duration": 4.319
    },
    {
      "text": "is critical",
      "start": 1218.559,
      "duration": 5.6
    },
    {
      "text": "critical to help heal us so what happens",
      "start": 1220.559,
      "duration": 5.761
    },
    {
      "text": "is this vitamin c in here",
      "start": 1224.159,
      "duration": 5.041
    },
    {
      "text": "goes straight to your immune system it",
      "start": 1226.32,
      "duration": 4.96
    },
    {
      "text": "doesn't go to the middle man it doesn't",
      "start": 1229.2,
      "duration": 2.4
    },
    {
      "text": "go",
      "start": 1231.28,
      "duration": 3.68
    },
    {
      "text": "to your liver it goes boom right to your",
      "start": 1231.6,
      "duration": 4.48
    },
    {
      "text": "lymphocytes",
      "start": 1234.96,
      "duration": 3.36
    },
    {
      "text": "boom right to your monocytes right to",
      "start": 1236.08,
      "duration": 3.36
    },
    {
      "text": "your neutrophils",
      "start": 1238.32,
      "duration": 3.04
    },
    {
      "text": "right to your basophils it goes into the",
      "start": 1239.44,
      "duration": 4.96
    },
    {
      "text": "immune system your white blood count",
      "start": 1241.36,
      "duration": 5.76
    },
    {
      "text": "gets it immediately and that's a big",
      "start": 1244.4,
      "duration": 4.24
    },
    {
      "text": "deal right there so i'm just telling you",
      "start": 1247.12,
      "duration": 3.919
    },
    {
      "text": "how orson vitamin c which is really cool",
      "start": 1248.64,
      "duration": 4.88
    },
    {
      "text": "and then and then the sodium cluster",
      "start": 1251.039,
      "duration": 4.561
    },
    {
      "text": "salts that are in celery juice too",
      "start": 1253.52,
      "duration": 5.279
    },
    {
      "text": "so sodium cluster salts in",
      "start": 1255.6,
      "duration": 5.76
    },
    {
      "text": "celery juice the subgroup of sodium",
      "start": 1258.799,
      "duration": 4.161
    },
    {
      "text": "that's undiscovered by research in",
      "start": 1261.36,
      "duration": 3.12
    },
    {
      "text": "science",
      "start": 1262.96,
      "duration": 4.24
    },
    {
      "text": "kills off bugs so it starts to kill off",
      "start": 1264.48,
      "duration": 3.88
    },
    {
      "text": "pathogens",
      "start": 1267.2,
      "duration": 4.24
    },
    {
      "text": "streptococcus in our system staph",
      "start": 1268.36,
      "duration": 6.28
    },
    {
      "text": "c diff epstein-barr cytomegalovirus",
      "start": 1271.44,
      "duration": 4.56
    },
    {
      "text": "herpes simplex 1",
      "start": 1274.64,
      "duration": 4.399
    },
    {
      "text": "herpes simplex 2 all this stuff",
      "start": 1276.0,
      "duration": 5.679
    },
    {
      "text": "and it and that sodium cluster salt",
      "start": 1279.039,
      "duration": 3.361
    },
    {
      "text": "inside",
      "start": 1281.679,
      "duration": 4.161
    },
    {
      "text": "this this um this this herbal medicine",
      "start": 1282.4,
      "duration": 4.8
    },
    {
      "text": "because that's what it is it's herbal",
      "start": 1285.84,
      "duration": 3.0
    },
    {
      "text": "medicine",
      "start": 1287.2,
      "duration": 5.2
    },
    {
      "text": "goes to the bugs and starts to weaken",
      "start": 1288.84,
      "duration": 4.199
    },
    {
      "text": "them",
      "start": 1292.4,
      "duration": 2.08
    },
    {
      "text": "starts to break them down if you got",
      "start": 1293.039,
      "duration": 3.361
    },
    {
      "text": "acne that's strep",
      "start": 1294.48,
      "duration": 4.4
    },
    {
      "text": "that's streptococcus if you have acne",
      "start": 1296.4,
      "duration": 4.56
    },
    {
      "text": "cystic acne is strep in your system and",
      "start": 1298.88,
      "duration": 4.159
    },
    {
      "text": "it and then your body",
      "start": 1300.96,
      "duration": 3.92
    },
    {
      "text": "puts all this builds up all the sebum",
      "start": 1303.039,
      "duration": 3.681
    },
    {
      "text": "oil to try to stop the strep and then it",
      "start": 1304.88,
      "duration": 3.919
    },
    {
      "text": "becomes nothing but a mess",
      "start": 1306.72,
      "duration": 4.4
    },
    {
      "text": "and this is good for that that's the",
      "start": 1308.799,
      "duration": 4.401
    },
    {
      "text": "whole thing in eczema psoriasis that's",
      "start": 1311.12,
      "duration": 3.28
    },
    {
      "text": "epstein-barr",
      "start": 1313.2,
      "duration": 2.88
    },
    {
      "text": "and copper inside the liver plus",
      "start": 1314.4,
      "duration": 4.48
    },
    {
      "text": "epstein-barr bar feeds off a copper",
      "start": 1316.08,
      "duration": 4.56
    },
    {
      "text": "and then it goes the bathroom then you",
      "start": 1318.88,
      "duration": 3.52
    },
    {
      "text": "got this dermatoxin well the celery",
      "start": 1320.64,
      "duration": 2.72
    },
    {
      "text": "juice",
      "start": 1322.4,
      "duration": 3.84
    },
    {
      "text": "goes into the liver and starts to clean",
      "start": 1323.36,
      "duration": 4.0
    },
    {
      "text": "up that ebv",
      "start": 1326.24,
      "duration": 2.799
    },
    {
      "text": "in there starts to break it down a",
      "start": 1327.36,
      "duration": 3.28
    },
    {
      "text": "little at a time little at a time and",
      "start": 1329.039,
      "duration": 3.361
    },
    {
      "text": "people start getting better",
      "start": 1330.64,
      "duration": 3.76
    },
    {
      "text": "and they start getting better how much",
      "start": 1332.4,
      "duration": 3.68
    },
    {
      "text": "are you supposed to drink a day",
      "start": 1334.4,
      "duration": 4.24
    },
    {
      "text": "i talk about all the different levels",
      "start": 1336.08,
      "duration": 4.479
    },
    {
      "text": "and dosages of what you can drink",
      "start": 1338.64,
      "duration": 4.48
    },
    {
      "text": "by the way this is on sale to all the",
      "start": 1340.559,
      "duration": 3.921
    },
    {
      "text": "medical media books i know that i told",
      "start": 1343.12,
      "duration": 2.559
    },
    {
      "text": "you guys yesterday",
      "start": 1344.48,
      "duration": 3.76
    },
    {
      "text": "they're on sale amazon.com us i told you",
      "start": 1345.679,
      "duration": 3.36
    },
    {
      "text": "about that",
      "start": 1348.24,
      "duration": 2.64
    },
    {
      "text": "but cleanse the heel i you can get it",
      "start": 1349.039,
      "duration": 3.52
    },
    {
      "text": "free at the library too you can go to",
      "start": 1350.88,
      "duration": 3.039
    },
    {
      "text": "the library get free",
      "start": 1352.559,
      "duration": 3.921
    },
    {
      "text": "library if you need to um but i talk",
      "start": 1353.919,
      "duration": 4.401
    },
    {
      "text": "about the different dosages",
      "start": 1356.48,
      "duration": 5.12
    },
    {
      "text": "of celery juice i like 16 ounces on an",
      "start": 1358.32,
      "duration": 4.32
    },
    {
      "text": "empty stomach",
      "start": 1361.6,
      "duration": 2.88
    },
    {
      "text": "great place to start if you need to go",
      "start": 1362.64,
      "duration": 3.84
    },
    {
      "text": "lower you can you can start lower than",
      "start": 1364.48,
      "duration": 4.24
    },
    {
      "text": "that you can if you need to",
      "start": 1366.48,
      "duration": 5.28
    },
    {
      "text": "that's perfectly fine you guys and",
      "start": 1368.72,
      "duration": 5.6
    },
    {
      "text": "but you can work yourself up to 32",
      "start": 1371.76,
      "duration": 4.24
    },
    {
      "text": "ounces a day",
      "start": 1374.32,
      "duration": 4.479
    },
    {
      "text": "and you can do 32 ounces in the morning",
      "start": 1376.0,
      "duration": 4.559
    },
    {
      "text": "so i like to do the lemon water first",
      "start": 1378.799,
      "duration": 3.36
    },
    {
      "text": "thing in the morning wait about a half",
      "start": 1380.559,
      "duration": 2.24
    },
    {
      "text": "an hour",
      "start": 1382.159,
      "duration": 3.601
    },
    {
      "text": "then i do my celery juice i go into that",
      "start": 1382.799,
      "duration": 5.441
    },
    {
      "text": "then after the celery juice i do my",
      "start": 1385.76,
      "duration": 4.24
    },
    {
      "text": "the medical medium heavy metal detox",
      "start": 1388.24,
      "duration": 3.52
    },
    {
      "text": "smoothie after that",
      "start": 1390.0,
      "duration": 3.28
    },
    {
      "text": "and that's where i go if you guys just",
      "start": 1391.76,
      "duration": 3.279
    },
    {
      "text": "got on here got the celery juice right",
      "start": 1393.28,
      "duration": 2.56
    },
    {
      "text": "here",
      "start": 1395.039,
      "duration": 4.961
    },
    {
      "text": "i just juiced it and this is what's left",
      "start": 1395.84,
      "duration": 6.079
    },
    {
      "text": "right there that's the pulp so if you've",
      "start": 1400.0,
      "duration": 4.24
    },
    {
      "text": "ever owned a juicer",
      "start": 1401.919,
      "duration": 4.321
    },
    {
      "text": "you'll know what this means this is like",
      "start": 1404.24,
      "duration": 3.2
    },
    {
      "text": "one of these like",
      "start": 1406.24,
      "duration": 3.439
    },
    {
      "text": "little miracles it's just it's it's",
      "start": 1407.44,
      "duration": 4.479
    },
    {
      "text": "incredible this is dry to the bone",
      "start": 1409.679,
      "duration": 4.641
    },
    {
      "text": "there's no juice in it it's not wet it's",
      "start": 1411.919,
      "duration": 4.561
    },
    {
      "text": "really really dry there's not much in",
      "start": 1414.32,
      "duration": 2.8
    },
    {
      "text": "here",
      "start": 1416.48,
      "duration": 2.4
    },
    {
      "text": "for all this celery juice and that's",
      "start": 1417.12,
      "duration": 3.76
    },
    {
      "text": "because this is a celery juicer even",
      "start": 1418.88,
      "duration": 4.0
    },
    {
      "text": "though it juices other stuff and",
      "start": 1420.88,
      "duration": 4.56
    },
    {
      "text": "and you can go to omega juicers.com",
      "start": 1422.88,
      "duration": 3.76
    },
    {
      "text": "omega",
      "start": 1425.44,
      "duration": 4.96
    },
    {
      "text": "juicers.com but you have to get the mm",
      "start": 1426.64,
      "duration": 6.56
    },
    {
      "text": "900 hds celery juicer because they got a",
      "start": 1430.4,
      "duration": 4.399
    },
    {
      "text": "lot of juice reserved this is the one",
      "start": 1433.2,
      "duration": 2.8
    },
    {
      "text": "that does it",
      "start": 1434.799,
      "duration": 4.721
    },
    {
      "text": "um can celery juice help with eczema",
      "start": 1436.0,
      "duration": 6.159
    },
    {
      "text": "mikey it already has for thousands of",
      "start": 1439.52,
      "duration": 3.44
    },
    {
      "text": "people",
      "start": 1442.159,
      "duration": 3.361
    },
    {
      "text": "it already has there's healing stories",
      "start": 1442.96,
      "duration": 3.92
    },
    {
      "text": "everywhere",
      "start": 1445.52,
      "duration": 4.639
    },
    {
      "text": "about people getting eczema to go away",
      "start": 1446.88,
      "duration": 6.799
    },
    {
      "text": "i mean it's it's already happened and so",
      "start": 1450.159,
      "duration": 6.241
    },
    {
      "text": "just so you know that yes you can get",
      "start": 1453.679,
      "duration": 3.441
    },
    {
      "text": "help with it",
      "start": 1456.4,
      "duration": 3.6
    },
    {
      "text": "is a healing tool for eczema because",
      "start": 1457.12,
      "duration": 4.32
    },
    {
      "text": "it's already happened",
      "start": 1460.0,
      "duration": 3.44
    },
    {
      "text": "everybody's claiming that with their",
      "start": 1461.44,
      "duration": 3.92
    },
    {
      "text": "healing process their eczema is going",
      "start": 1463.44,
      "duration": 2.64
    },
    {
      "text": "away so",
      "start": 1465.36,
      "duration": 3.439
    },
    {
      "text": "it's already out there so you know and",
      "start": 1466.08,
      "duration": 4.8
    },
    {
      "text": "that's cool if you check out",
      "start": 1468.799,
      "duration": 4.081
    },
    {
      "text": "you check out the the medical medium",
      "start": 1470.88,
      "duration": 3.12
    },
    {
      "text": "instagram",
      "start": 1472.88,
      "duration": 3.039
    },
    {
      "text": "medical me and facebook and you'll see",
      "start": 1474.0,
      "duration": 4.08
    },
    {
      "text": "the healing stories of people in their",
      "start": 1475.919,
      "duration": 3.201
    },
    {
      "text": "eczema",
      "start": 1478.08,
      "duration": 2.8
    },
    {
      "text": "and you'll see what's going on and",
      "start": 1479.12,
      "duration": 3.52
    },
    {
      "text": "they're using sub they're doing celery",
      "start": 1480.88,
      "duration": 3.52
    },
    {
      "text": "juice every single day",
      "start": 1482.64,
      "duration": 3.2
    },
    {
      "text": "and they're doing other medical medium",
      "start": 1484.4,
      "duration": 3.12
    },
    {
      "text": "tools which are helpful too but the",
      "start": 1485.84,
      "duration": 4.0
    },
    {
      "text": "cellular juice is a big part of how we",
      "start": 1487.52,
      "duration": 4.08
    },
    {
      "text": "can heal skin issues",
      "start": 1489.84,
      "duration": 4.079
    },
    {
      "text": "it's a great thing to do um daniel",
      "start": 1491.6,
      "duration": 3.84
    },
    {
      "text": "vitiligo too",
      "start": 1493.919,
      "duration": 5.281
    },
    {
      "text": "exactly that's a skin condition vitiligo",
      "start": 1495.44,
      "duration": 6.8
    },
    {
      "text": "that's having aluminum in your liver so",
      "start": 1499.2,
      "duration": 5.04
    },
    {
      "text": "celery juice here's another benefit of",
      "start": 1502.24,
      "duration": 3.2
    },
    {
      "text": "celery juice too",
      "start": 1504.24,
      "duration": 3.919
    },
    {
      "text": "okay it goes into the liver and it",
      "start": 1505.44,
      "duration": 4.32
    },
    {
      "text": "starts to clean it up",
      "start": 1508.159,
      "duration": 5.12
    },
    {
      "text": "it starts to flush it out",
      "start": 1509.76,
      "duration": 6.32
    },
    {
      "text": "and what's in our liver petrochemicals",
      "start": 1513.279,
      "duration": 4.0
    },
    {
      "text": "ddt",
      "start": 1516.08,
      "duration": 3.28
    },
    {
      "text": "herbicides pesticides rodenticides",
      "start": 1517.279,
      "duration": 4.4
    },
    {
      "text": "insecticides all sit inside our liver",
      "start": 1519.36,
      "duration": 4.319
    },
    {
      "text": "gasoline from the pumps when you pump",
      "start": 1521.679,
      "duration": 3.761
    },
    {
      "text": "gas and you're breathing in the fumes",
      "start": 1523.679,
      "duration": 3.681
    },
    {
      "text": "goes inside the liver plastics",
      "start": 1525.44,
      "duration": 4.16
    },
    {
      "text": "go inside the liver pharmaceuticals",
      "start": 1527.36,
      "duration": 3.72
    },
    {
      "text": "antibiotics",
      "start": 1529.6,
      "duration": 4.48
    },
    {
      "text": "benzodiazepines anti-inflammatories",
      "start": 1531.08,
      "duration": 4.68
    },
    {
      "text": "any kind of drug or medication you've",
      "start": 1534.08,
      "duration": 4.0
    },
    {
      "text": "taken throughout your life goes into the",
      "start": 1535.76,
      "duration": 3.2
    },
    {
      "text": "liver",
      "start": 1538.08,
      "duration": 2.88
    },
    {
      "text": "thyroid medications go into the liver",
      "start": 1538.96,
      "duration": 3.44
    },
    {
      "text": "and it gets stagnant",
      "start": 1540.96,
      "duration": 4.4
    },
    {
      "text": "sluggish and then in that liver is also",
      "start": 1542.4,
      "duration": 4.08
    },
    {
      "text": "little buggies",
      "start": 1545.36,
      "duration": 2.88
    },
    {
      "text": "the epstein bar that's a big one that",
      "start": 1546.48,
      "duration": 3.04
    },
    {
      "text": "sits inside the liver",
      "start": 1548.24,
      "duration": 3.28
    },
    {
      "text": "so if you have toxic heavy metals in",
      "start": 1549.52,
      "duration": 4.639
    },
    {
      "text": "there too copper lead arsenic aluminum",
      "start": 1551.52,
      "duration": 6.56
    },
    {
      "text": "mercury cadmium nickel inside your liver",
      "start": 1554.159,
      "duration": 7.681
    },
    {
      "text": "that copper and other metals feed",
      "start": 1558.08,
      "duration": 7.599
    },
    {
      "text": "viruses then a dermatoxin is produced",
      "start": 1561.84,
      "duration": 6.56
    },
    {
      "text": "and an aluminum-based one for vitiligo",
      "start": 1565.679,
      "duration": 4.24
    },
    {
      "text": "and you lose your melon and you lose the",
      "start": 1568.4,
      "duration": 3.36
    },
    {
      "text": "pigment that's how it works celery juice",
      "start": 1569.919,
      "duration": 3.041
    },
    {
      "text": "goes into the liver",
      "start": 1571.76,
      "duration": 3.68
    },
    {
      "text": "and it starts to do some healing plus",
      "start": 1572.96,
      "duration": 4.4
    },
    {
      "text": "it's got phytochemical compounds that",
      "start": 1575.44,
      "duration": 4.8
    },
    {
      "text": "help heal the skin and i talk about that",
      "start": 1577.36,
      "duration": 4.4
    },
    {
      "text": "in celery juice book which is really",
      "start": 1580.24,
      "duration": 2.6
    },
    {
      "text": "cool",
      "start": 1581.76,
      "duration": 4.0
    },
    {
      "text": "um so yeah",
      "start": 1582.84,
      "duration": 4.439
    },
    {
      "text": "i'm reading some more comments checking",
      "start": 1585.76,
      "duration": 3.039
    },
    {
      "text": "things out trying to help in any way i",
      "start": 1587.279,
      "duration": 2.64
    },
    {
      "text": "can't talk",
      "start": 1588.799,
      "duration": 4.88
    },
    {
      "text": "dana said darn ebv i know i know it's no",
      "start": 1589.919,
      "duration": 5.201
    },
    {
      "text": "fun it causes a lot of trouble",
      "start": 1593.679,
      "duration": 3.6
    },
    {
      "text": "causes the fibromyalgia hashimoto's",
      "start": 1595.12,
      "duration": 3.439
    },
    {
      "text": "thyroiditis r.a",
      "start": 1597.279,
      "duration": 3.121
    },
    {
      "text": "lyme disease it causes a lot of trouble",
      "start": 1598.559,
      "duration": 3.281
    },
    {
      "text": "in a lot of people there's different",
      "start": 1600.4,
      "duration": 3.92
    },
    {
      "text": "varieties there's over 60 varieties",
      "start": 1601.84,
      "duration": 6.079
    },
    {
      "text": "of epstein-barr and research and science",
      "start": 1604.32,
      "duration": 4.719
    },
    {
      "text": "doesn't even know that they thought",
      "start": 1607.919,
      "duration": 2.721
    },
    {
      "text": "epstein-barr just did this you know what",
      "start": 1609.039,
      "duration": 2.24
    },
    {
      "text": "they thought",
      "start": 1610.64,
      "duration": 2.32
    },
    {
      "text": "barr did all these years they thought it",
      "start": 1611.279,
      "duration": 3.361
    },
    {
      "text": "just made somebody tired",
      "start": 1612.96,
      "duration": 3.52
    },
    {
      "text": "and gave them a mild fever when they had",
      "start": 1614.64,
      "duration": 4.0
    },
    {
      "text": "mono that's it that's all they knew",
      "start": 1616.48,
      "duration": 3.84
    },
    {
      "text": "medical media information and books",
      "start": 1618.64,
      "duration": 3.44
    },
    {
      "text": "published that epstein-barr causes all",
      "start": 1620.32,
      "duration": 2.719
    },
    {
      "text": "these conditions",
      "start": 1622.08,
      "duration": 4.24
    },
    {
      "text": "and guess what a few years later after",
      "start": 1623.039,
      "duration": 4.801
    },
    {
      "text": "millions of books went into doctor's",
      "start": 1626.32,
      "duration": 3.04
    },
    {
      "text": "offices uh",
      "start": 1627.84,
      "duration": 4.48
    },
    {
      "text": "a few years later they decided to say uh",
      "start": 1629.36,
      "duration": 3.76
    },
    {
      "text": "they think",
      "start": 1632.32,
      "duration": 2.56
    },
    {
      "text": "now epstein barr is linked to",
      "start": 1633.12,
      "duration": 4.159
    },
    {
      "text": "hashimoto's they think it's linked now",
      "start": 1634.88,
      "duration": 3.36
    },
    {
      "text": "to r.a",
      "start": 1637.279,
      "duration": 2.801
    },
    {
      "text": "they think it's linked now to",
      "start": 1638.24,
      "duration": 3.439
    },
    {
      "text": "neurological lime",
      "start": 1640.08,
      "duration": 2.959
    },
    {
      "text": "for medical medium information it's",
      "start": 1641.679,
      "duration": 3.36
    },
    {
      "text": "pretty pretty amazing really what's",
      "start": 1643.039,
      "duration": 2.801
    },
    {
      "text": "happened",
      "start": 1645.039,
      "duration": 3.201
    },
    {
      "text": "and it's really great it's really great",
      "start": 1645.84,
      "duration": 4.48
    },
    {
      "text": "um can we give",
      "start": 1648.24,
      "duration": 5.52
    },
    {
      "text": "the wildlife celery juice",
      "start": 1650.32,
      "duration": 6.0
    },
    {
      "text": "because of chemtrails is that i think",
      "start": 1653.76,
      "duration": 3.84
    },
    {
      "text": "that's what you're saying the",
      "start": 1656.32,
      "duration": 4.4
    },
    {
      "text": "wildlife i don't know i mean you can",
      "start": 1657.6,
      "duration": 5.76
    },
    {
      "text": "look i i got squirrels i put out little",
      "start": 1660.72,
      "duration": 6.48
    },
    {
      "text": "pieces of celery and squirrels eaten",
      "start": 1663.36,
      "duration": 3.84
    },
    {
      "text": "out there for squirrels um and i think",
      "start": 1667.6,
      "duration": 4.799
    },
    {
      "text": "the question i think was confused by the",
      "start": 1670.88,
      "duration": 2.56
    },
    {
      "text": "question or the con",
      "start": 1672.399,
      "duration": 2.321
    },
    {
      "text": "the question probably a little different",
      "start": 1673.44,
      "duration": 4.479
    },
    {
      "text": "than what it looks like um",
      "start": 1674.72,
      "duration": 4.88
    },
    {
      "text": "yeah ingrid you could use limes instead",
      "start": 1677.919,
      "duration": 3.201
    },
    {
      "text": "of lemon i just saw that",
      "start": 1679.6,
      "duration": 3.12
    },
    {
      "text": "in your lemon water you can have lime",
      "start": 1681.12,
      "duration": 3.36
    },
    {
      "text": "water if you really need to that's okay",
      "start": 1682.72,
      "duration": 2.24
    },
    {
      "text": "too",
      "start": 1684.48,
      "duration": 4.079
    },
    {
      "text": "you can do that so yeah",
      "start": 1684.96,
      "duration": 6.56
    },
    {
      "text": "so you guys the thing is here is that",
      "start": 1688.559,
      "duration": 5.281
    },
    {
      "text": "when it comes down to celery juice",
      "start": 1691.52,
      "duration": 4.56
    },
    {
      "text": "you're helping your body heal and that's",
      "start": 1693.84,
      "duration": 3.04
    },
    {
      "text": "a big deal",
      "start": 1696.08,
      "duration": 3.28
    },
    {
      "text": "and if you're somebody that's not sick",
      "start": 1696.88,
      "duration": 4.159
    },
    {
      "text": "and you're not worried about healing",
      "start": 1699.36,
      "duration": 4.24
    },
    {
      "text": "it's still good because it can actually",
      "start": 1701.039,
      "duration": 4.161
    },
    {
      "text": "prevent things and that's what i love",
      "start": 1703.6,
      "duration": 3.12
    },
    {
      "text": "about celery juice",
      "start": 1705.2,
      "duration": 4.0
    },
    {
      "text": "that's why i drink it every single day i",
      "start": 1706.72,
      "duration": 4.0
    },
    {
      "text": "drink it every day think of a single day",
      "start": 1709.2,
      "duration": 2.959
    },
    {
      "text": "because i want to stay healthy",
      "start": 1710.72,
      "duration": 3.6
    },
    {
      "text": "i want to make sure i stay strong i stay",
      "start": 1712.159,
      "duration": 4.24
    },
    {
      "text": "hot stay healthy i drink it every single",
      "start": 1714.32,
      "duration": 4.239
    },
    {
      "text": "day because of that",
      "start": 1716.399,
      "duration": 4.081
    },
    {
      "text": "and you feed laurie you feed your dog",
      "start": 1718.559,
      "duration": 3.521
    },
    {
      "text": "celery that's really cool",
      "start": 1720.48,
      "duration": 6.799
    },
    {
      "text": "dogs love celery they do they do um",
      "start": 1722.08,
      "duration": 7.36
    },
    {
      "text": "whoa you're dakarya whoa celery juices",
      "start": 1727.279,
      "duration": 4.161
    },
    {
      "text": "help that incredible i'm seeing a lot of",
      "start": 1729.44,
      "duration": 2.959
    },
    {
      "text": "celery juice",
      "start": 1731.44,
      "duration": 3.839
    },
    {
      "text": "helping a lot of people it's really",
      "start": 1732.399,
      "duration": 3.601
    },
    {
      "text": "amazing",
      "start": 1735.279,
      "duration": 4.0
    },
    {
      "text": "when you think about it so you guys",
      "start": 1736.0,
      "duration": 5.44
    },
    {
      "text": "um this is easy to clean by the way let",
      "start": 1739.279,
      "duration": 4.481
    },
    {
      "text": "me run let me run that by you too",
      "start": 1741.44,
      "duration": 5.119
    },
    {
      "text": "lorraine l says she loves squirrels um",
      "start": 1743.76,
      "duration": 4.48
    },
    {
      "text": "this is easy to clean",
      "start": 1746.559,
      "duration": 3.6
    },
    {
      "text": "that's what i love about this one too",
      "start": 1748.24,
      "duration": 4.08
    },
    {
      "text": "it's easy to dismantle all you do is you",
      "start": 1750.159,
      "duration": 3.681
    },
    {
      "text": "just take off this little piece right",
      "start": 1752.32,
      "duration": 1.92
    },
    {
      "text": "here",
      "start": 1753.84,
      "duration": 3.28
    },
    {
      "text": "like that and then you actually take off",
      "start": 1754.24,
      "duration": 4.0
    },
    {
      "text": "this piece too",
      "start": 1757.12,
      "duration": 2.799
    },
    {
      "text": "and then you're good you actually can",
      "start": 1758.24,
      "duration": 3.2
    },
    {
      "text": "clean it and you're all set you can take",
      "start": 1759.919,
      "duration": 2.561
    },
    {
      "text": "off this",
      "start": 1761.44,
      "duration": 2.56
    },
    {
      "text": "and now you got this whole piece right",
      "start": 1762.48,
      "duration": 3.28
    },
    {
      "text": "here and then you just take it apart",
      "start": 1764.0,
      "duration": 3.12
    },
    {
      "text": "it's really simple to clean",
      "start": 1765.76,
      "duration": 3.68
    },
    {
      "text": "it's really easy to clean i love this",
      "start": 1767.12,
      "duration": 3.039
    },
    {
      "text": "juicer",
      "start": 1769.44,
      "duration": 3.92
    },
    {
      "text": "so check it out when you can so",
      "start": 1770.159,
      "duration": 5.441
    },
    {
      "text": "32 over 32 ounces i still got a little",
      "start": 1773.36,
      "duration": 4.72
    },
    {
      "text": "bit left in a container right here",
      "start": 1775.6,
      "duration": 5.36
    },
    {
      "text": "and that's how much pulp which is",
      "start": 1778.08,
      "duration": 4.719
    },
    {
      "text": "ridiculous right there",
      "start": 1780.96,
      "duration": 5.68
    },
    {
      "text": "but um you guys i'm heading over now to",
      "start": 1782.799,
      "duration": 6.0
    },
    {
      "text": "ig if you want to come with me after ig",
      "start": 1786.64,
      "duration": 3.919
    },
    {
      "text": "i'm going to tick tock after that",
      "start": 1788.799,
      "duration": 3.681
    },
    {
      "text": "so i'm going to juice again talk about",
      "start": 1790.559,
      "duration": 3.12
    },
    {
      "text": "it i think there's some stuff i didn't",
      "start": 1792.48,
      "duration": 2.24
    },
    {
      "text": "even cover",
      "start": 1793.679,
      "duration": 2.401
    },
    {
      "text": "so that's what happens usually there's",
      "start": 1794.72,
      "duration": 2.559
    },
    {
      "text": "stuff and i'm gonna answer some more",
      "start": 1796.08,
      "duration": 2.24
    },
    {
      "text": "questions too",
      "start": 1797.279,
      "duration": 4.481
    },
    {
      "text": "um yeah that's this is a cold pressed",
      "start": 1798.32,
      "duration": 4.079
    },
    {
      "text": "one",
      "start": 1801.76,
      "duration": 2.88
    },
    {
      "text": "this is a cold pressed juicer you guys",
      "start": 1802.399,
      "duration": 3.76
    },
    {
      "text": "should be doing the moon meditation",
      "start": 1804.64,
      "duration": 4.0
    },
    {
      "text": "it's a full moon should totally be doing",
      "start": 1806.159,
      "duration": 4.481
    },
    {
      "text": "if you can medical meeting podcast at",
      "start": 1808.64,
      "duration": 4.0
    },
    {
      "text": "apple podcast the moon meditation it's",
      "start": 1810.64,
      "duration": 3.12
    },
    {
      "text": "free",
      "start": 1812.64,
      "duration": 3.84
    },
    {
      "text": "it's a powerful meditation we're right",
      "start": 1813.76,
      "duration": 4.399
    },
    {
      "text": "around the full moon right now",
      "start": 1816.48,
      "duration": 3.439
    },
    {
      "text": "you guys should be doing it every i did",
      "start": 1818.159,
      "duration": 3.841
    },
    {
      "text": "it last night did it the night before",
      "start": 1819.919,
      "duration": 3.601
    },
    {
      "text": "you guys should do the moon meditation",
      "start": 1822.0,
      "duration": 3.44
    },
    {
      "text": "when you get a chance it's really",
      "start": 1823.52,
      "duration": 4.0
    },
    {
      "text": "healing it's healing for the soul",
      "start": 1825.44,
      "duration": 3.68
    },
    {
      "text": "check it out if you can medical medium",
      "start": 1827.52,
      "duration": 3.12
    },
    {
      "text": "podcast at apple podcast",
      "start": 1829.12,
      "duration": 3.76
    },
    {
      "text": "everybody should be doing it right now",
      "start": 1830.64,
      "duration": 4.399
    },
    {
      "text": "and take advantage of it the magnetic",
      "start": 1832.88,
      "duration": 3.279
    },
    {
      "text": "pull of the moon",
      "start": 1835.039,
      "duration": 4.0
    },
    {
      "text": "and the healing power it has on the soul",
      "start": 1836.159,
      "duration": 5.041
    },
    {
      "text": "on the spirit on the heart from wounds",
      "start": 1839.039,
      "duration": 3.36
    },
    {
      "text": "emotional wounds",
      "start": 1841.2,
      "duration": 3.76
    },
    {
      "text": "i talk about that all the time you know",
      "start": 1842.399,
      "duration": 4.64
    },
    {
      "text": "the betrayal broken trust broken",
      "start": 1844.96,
      "duration": 3.12
    },
    {
      "text": "promises",
      "start": 1847.039,
      "duration": 3.921
    },
    {
      "text": "losses emotional struggles the moon",
      "start": 1848.08,
      "duration": 4.479
    },
    {
      "text": "meditation hope you guys are doing it",
      "start": 1850.96,
      "duration": 2.959
    },
    {
      "text": "when you get the chance",
      "start": 1852.559,
      "duration": 3.761
    },
    {
      "text": "yes the moon is out and it's bright",
      "start": 1853.919,
      "duration": 3.521
    },
    {
      "text": "that's incredible",
      "start": 1856.32,
      "duration": 3.04
    },
    {
      "text": "in munich that's amazing and so if you",
      "start": 1857.44,
      "duration": 3.2
    },
    {
      "text": "get a chance go to medical medium",
      "start": 1859.36,
      "duration": 3.679
    },
    {
      "text": "podcast at apple podcast",
      "start": 1860.64,
      "duration": 4.24
    },
    {
      "text": "vanilla says did the moon meditation",
      "start": 1863.039,
      "duration": 3.201
    },
    {
      "text": "last night 100",
      "start": 1864.88,
      "duration": 4.32
    },
    {
      "text": "full moon incredible guys do it again",
      "start": 1866.24,
      "duration": 4.559
    },
    {
      "text": "tonight i'm doing again tonight",
      "start": 1869.2,
      "duration": 3.28
    },
    {
      "text": "when you get a chance i'll see i'm going",
      "start": 1870.799,
      "duration": 3.521
    },
    {
      "text": "to ig right now bless your heart just",
      "start": 1872.48,
      "duration": 2.72
    },
    {
      "text": "know that i care",
      "start": 1874.32,
      "duration": 3.52
    },
    {
      "text": "you guys are amazed",
      "start": 1875.2,
      "duration": 2.64
    }
  ],
  "is_generated": true
}