{
  "video_id": "sLBWntJ1lT4",
  "language": "English (auto-generated)",
  "language_code": "en",
  "subtitles": [
    {
      "text": "get sick what are the causes of sickness",
      "start": 0.0,
      "duration": 3.679
    },
    {
      "text": "why does everybody go around",
      "start": 1.68,
      "duration": 4.079
    },
    {
      "text": "looking for answers and they think they",
      "start": 3.679,
      "duration": 3.6
    },
    {
      "text": "have an answer but they really don't",
      "start": 5.759,
      "duration": 3.281
    },
    {
      "text": "have an answer and then they stay sick",
      "start": 7.279,
      "duration": 3.601
    },
    {
      "text": "another two months another six months",
      "start": 9.04,
      "duration": 3.92
    },
    {
      "text": "and then two years go by and then five",
      "start": 10.88,
      "duration": 4.56
    },
    {
      "text": "years go by and then 10 years go by i",
      "start": 12.96,
      "duration": 4.079
    },
    {
      "text": "remember people coming to my office many",
      "start": 15.44,
      "duration": 4.48
    },
    {
      "text": "years ago with 30 years have gone by",
      "start": 17.039,
      "duration": 5.441
    },
    {
      "text": "sick hashimoto's thyroid problems on",
      "start": 19.92,
      "duration": 4.4
    },
    {
      "text": "thyroid medications all kinds of blood",
      "start": 22.48,
      "duration": 3.52
    },
    {
      "text": "pressure problems all kinds of nerve",
      "start": 24.32,
      "duration": 4.16
    },
    {
      "text": "problems restless leg syndrome insomnia",
      "start": 26.0,
      "duration": 4.16
    },
    {
      "text": "you name it they're on pills they're on",
      "start": 28.48,
      "duration": 3.199
    },
    {
      "text": "this they got high anxiety they got",
      "start": 30.16,
      "duration": 2.8
    },
    {
      "text": "depression it's like how long you've",
      "start": 31.679,
      "duration": 3.921
    },
    {
      "text": "been sick been sick for 25 years i'm",
      "start": 32.96,
      "duration": 4.72
    },
    {
      "text": "like oh my god and then they get the",
      "start": 35.6,
      "duration": 4.0
    },
    {
      "text": "answers and things start going away and",
      "start": 37.68,
      "duration": 3.52
    },
    {
      "text": "as things start going away they go",
      "start": 39.6,
      "duration": 4.56
    },
    {
      "text": "anthony why didn't i find you 25 years",
      "start": 41.2,
      "duration": 5.92
    },
    {
      "text": "ago and i'm like well",
      "start": 44.16,
      "duration": 5.84
    },
    {
      "text": "since this is 25 years ago",
      "start": 47.12,
      "duration": 5.439
    },
    {
      "text": "uh 25 years before that i would have",
      "start": 50.0,
      "duration": 5.52
    },
    {
      "text": "been very little so the point is is",
      "start": 52.559,
      "duration": 4.561
    },
    {
      "text": "people just they go around they look",
      "start": 55.52,
      "duration": 3.839
    },
    {
      "text": "around if they're trying to find help",
      "start": 57.12,
      "duration": 4.4
    },
    {
      "text": "and they can't find the answers and yet",
      "start": 59.359,
      "duration": 3.761
    },
    {
      "text": "this is a special time and it's not",
      "start": 61.52,
      "duration": 3.359
    },
    {
      "text": "about me it's not because i'm special or",
      "start": 63.12,
      "duration": 3.6
    },
    {
      "text": "anything like that is because",
      "start": 64.879,
      "duration": 4.801
    },
    {
      "text": "we have answers now it's it's the",
      "start": 66.72,
      "duration": 5.12
    },
    {
      "text": "information i get from the source i hear",
      "start": 69.68,
      "duration": 4.16
    },
    {
      "text": "right whether somebody likes that or not",
      "start": 71.84,
      "duration": 4.4
    },
    {
      "text": "or somebody thinks it sounds kind of you",
      "start": 73.84,
      "duration": 5.52
    },
    {
      "text": "know crazy or whatever it is a fact it's",
      "start": 76.24,
      "duration": 5.76
    },
    {
      "text": "a fact since age four i've been hearing",
      "start": 79.36,
      "duration": 5.84
    },
    {
      "text": "a voice that voice tells me why people",
      "start": 82.0,
      "duration": 5.439
    },
    {
      "text": "are sick and what's wrong and what they",
      "start": 85.2,
      "duration": 3.599
    },
    {
      "text": "need and",
      "start": 87.439,
      "duration": 4.161
    },
    {
      "text": "thousands and thousands of people got",
      "start": 88.799,
      "duration": 4.96
    },
    {
      "text": "their lives back and man when you're",
      "start": 91.6,
      "duration": 3.839
    },
    {
      "text": "praying to god and you're down on your",
      "start": 93.759,
      "duration": 3.601
    },
    {
      "text": "knees and you're like i got no hope left",
      "start": 95.439,
      "duration": 4.481
    },
    {
      "text": "i can't go to work i can't function my",
      "start": 97.36,
      "duration": 5.439
    },
    {
      "text": "anxiety is killing me the answers matter",
      "start": 99.92,
      "duration": 4.64
    },
    {
      "text": "and that's what happened cindy lou cindy",
      "start": 102.799,
      "duration": 3.121
    },
    {
      "text": "lou what's going on you always leave",
      "start": 104.56,
      "duration": 2.48
    },
    {
      "text": "comments on",
      "start": 105.92,
      "duration": 3.12
    },
    {
      "text": "i always leave comments on the uh on the",
      "start": 107.04,
      "duration": 4.0
    },
    {
      "text": "youtube all the time right here you are",
      "start": 109.04,
      "duration": 5.039
    },
    {
      "text": "that was a quick kitchen clean right",
      "start": 111.04,
      "duration": 5.2
    },
    {
      "text": "yeah i know we just did the amazon live",
      "start": 114.079,
      "duration": 3.761
    },
    {
      "text": "you guys we made waffles ten different",
      "start": 116.24,
      "duration": 3.36
    },
    {
      "text": "ways it was crazy it was like peanut",
      "start": 117.84,
      "duration": 3.84
    },
    {
      "text": "butter waffles like almond butter wild i",
      "start": 119.6,
      "duration": 3.6
    },
    {
      "text": "don't know what tahini waffles that's",
      "start": 121.68,
      "duration": 3.36
    },
    {
      "text": "what it was it was refried beans waffles",
      "start": 123.2,
      "duration": 2.879
    },
    {
      "text": "where it was like",
      "start": 125.04,
      "duration": 3.12
    },
    {
      "text": "it was pico waffles it was like",
      "start": 126.079,
      "duration": 4.32
    },
    {
      "text": "everything nacho waffles man it was",
      "start": 128.16,
      "duration": 3.6
    },
    {
      "text": "crazy it was incredible cold white",
      "start": 130.399,
      "duration": 3.441
    },
    {
      "text": "spring good to see you right you see the",
      "start": 131.76,
      "duration": 3.92
    },
    {
      "text": "moose cold night spring may you see the",
      "start": 133.84,
      "duration": 3.84
    },
    {
      "text": "moose yeah",
      "start": 135.68,
      "duration": 4.88
    },
    {
      "text": "it's pretty funny right so",
      "start": 137.68,
      "duration": 4.4
    },
    {
      "text": "nat says anthony can you help me with",
      "start": 140.56,
      "duration": 3.44
    },
    {
      "text": "trigeminal neuralgia please been",
      "start": 142.08,
      "duration": 3.6
    },
    {
      "text": "following protocol for two months no",
      "start": 144.0,
      "duration": 3.28
    },
    {
      "text": "results yet so here's what happens now",
      "start": 145.68,
      "duration": 3.44
    },
    {
      "text": "with trigeminal neuralgia right i've",
      "start": 147.28,
      "duration": 3.2
    },
    {
      "text": "talked to a lot of doctors about this",
      "start": 149.12,
      "duration": 3.04
    },
    {
      "text": "that have come to me because they i know",
      "start": 150.48,
      "duration": 2.96
    },
    {
      "text": "doctors that deal with trigeminal",
      "start": 152.16,
      "duration": 3.359
    },
    {
      "text": "neuralgia and they in their cases lots",
      "start": 153.44,
      "duration": 3.439
    },
    {
      "text": "of cases and i've taught them a lot of",
      "start": 155.519,
      "duration": 2.881
    },
    {
      "text": "things and one thing that's critical to",
      "start": 156.879,
      "duration": 3.761
    },
    {
      "text": "know about trigeminal neuralgia",
      "start": 158.4,
      "duration": 3.76
    },
    {
      "text": "is that you can have the shingles virus",
      "start": 160.64,
      "duration": 3.92
    },
    {
      "text": "causing trigeminal neuralgia and you can",
      "start": 162.16,
      "duration": 4.56
    },
    {
      "text": "even have the simplex one fever blister",
      "start": 164.56,
      "duration": 4.24
    },
    {
      "text": "cold sore that you don't even see so you",
      "start": 166.72,
      "duration": 4.159
    },
    {
      "text": "don't even have the cold sore or fever",
      "start": 168.8,
      "duration": 5.12
    },
    {
      "text": "blister but it's in the nerves it's in",
      "start": 170.879,
      "duration": 4.561
    },
    {
      "text": "the cranial nerve so let's do this a",
      "start": 173.92,
      "duration": 2.64
    },
    {
      "text": "little bit because we're going to talk",
      "start": 175.44,
      "duration": 2.879
    },
    {
      "text": "about this now why do we get trigeminal",
      "start": 176.56,
      "duration": 3.039
    },
    {
      "text": "neuralgia",
      "start": 178.319,
      "duration": 4.321
    },
    {
      "text": "because of a low-grade viral infection a",
      "start": 179.599,
      "duration": 5.761
    },
    {
      "text": "low-grade viral infection and that",
      "start": 182.64,
      "duration": 4.64
    },
    {
      "text": "low-grade viral infection are these",
      "start": 185.36,
      "duration": 3.28
    },
    {
      "text": "little bugs right here that's the",
      "start": 187.28,
      "duration": 2.959
    },
    {
      "text": "low-grade viral infection right here",
      "start": 188.64,
      "duration": 3.04
    },
    {
      "text": "it's these bugs",
      "start": 190.239,
      "duration": 3.681
    },
    {
      "text": "and these bugs sit inside of us right",
      "start": 191.68,
      "duration": 5.12
    },
    {
      "text": "and so it takes time for some stubborn",
      "start": 193.92,
      "duration": 6.239
    },
    {
      "text": "stubborn trigeminal neuralgia cases take",
      "start": 196.8,
      "duration": 5.439
    },
    {
      "text": "time gotta make sure there's no gluten",
      "start": 200.159,
      "duration": 3.36
    },
    {
      "text": "there you gotta make sure there's no",
      "start": 202.239,
      "duration": 3.201
    },
    {
      "text": "eggs in there you gotta make sure",
      "start": 203.519,
      "duration": 4.161
    },
    {
      "text": "there's no dairy products you gotta make",
      "start": 205.44,
      "duration": 5.6
    },
    {
      "text": "sure that you're keeping the fats low",
      "start": 207.68,
      "duration": 5.68
    },
    {
      "text": "low you got to make sure and then",
      "start": 211.04,
      "duration": 4.559
    },
    {
      "text": "protocols what protocols are you on",
      "start": 213.36,
      "duration": 4.48
    },
    {
      "text": "right and that's important too",
      "start": 215.599,
      "duration": 3.36
    },
    {
      "text": "right",
      "start": 217.84,
      "duration": 3.039
    },
    {
      "text": "how far are you on the protocol what's",
      "start": 218.959,
      "duration": 4.081
    },
    {
      "text": "going on there if i had trigeminal",
      "start": 220.879,
      "duration": 4.161
    },
    {
      "text": "neuralgia i'd be doing the protocol and",
      "start": 223.04,
      "duration": 3.52
    },
    {
      "text": "i would be you know taking a look in",
      "start": 225.04,
      "duration": 2.64
    },
    {
      "text": "here and you'll see all the different",
      "start": 226.56,
      "duration": 3.599
    },
    {
      "text": "stuff with the protocol right here and",
      "start": 227.68,
      "duration": 4.32
    },
    {
      "text": "you make sure you're on your vitamin c",
      "start": 230.159,
      "duration": 3.601
    },
    {
      "text": "make sure you're on there b12 you make",
      "start": 232.0,
      "duration": 3.519
    },
    {
      "text": "sure you're on your your different",
      "start": 233.76,
      "duration": 3.199
    },
    {
      "text": "things that you need",
      "start": 235.519,
      "duration": 3.761
    },
    {
      "text": "zinc is critical too now ask your doctor",
      "start": 236.959,
      "duration": 3.521
    },
    {
      "text": "what's right for you but if i had",
      "start": 239.28,
      "duration": 3.2
    },
    {
      "text": "trigeminal neuralgia",
      "start": 240.48,
      "duration": 3.039
    },
    {
      "text": "i'd be",
      "start": 242.48,
      "duration": 4.319
    },
    {
      "text": "i'd be 100 fat free if it was bad if i",
      "start": 243.519,
      "duration": 5.28
    },
    {
      "text": "was suffering 100",
      "start": 246.799,
      "duration": 3.761
    },
    {
      "text": "no fats right",
      "start": 248.799,
      "duration": 4.481
    },
    {
      "text": "i'd be doing i'd be doing the papaya",
      "start": 250.56,
      "duration": 5.28
    },
    {
      "text": "banana mono cleanse possibly be doing",
      "start": 253.28,
      "duration": 4.56
    },
    {
      "text": "the heavy metal detox smoothie i'd have",
      "start": 255.84,
      "duration": 3.679
    },
    {
      "text": "that in there you know you can pick and",
      "start": 257.84,
      "duration": 4.16
    },
    {
      "text": "choose what you feel like doing but you",
      "start": 259.519,
      "duration": 4.721
    },
    {
      "text": "can get there one thing's for sure is",
      "start": 262.0,
      "duration": 3.759
    },
    {
      "text": "i'd stay away from the eggs the gluten",
      "start": 264.24,
      "duration": 3.04
    },
    {
      "text": "the dairy products if i had a",
      "start": 265.759,
      "duration": 2.961
    },
    {
      "text": "neurologist stay away from all of that",
      "start": 267.28,
      "duration": 4.16
    },
    {
      "text": "keep the fats down to zero if you can",
      "start": 268.72,
      "duration": 5.12
    },
    {
      "text": "and then get the antivirals in that are",
      "start": 271.44,
      "duration": 4.64
    },
    {
      "text": "in cleanse the heal right because you're",
      "start": 273.84,
      "duration": 4.48
    },
    {
      "text": "looking at knocking out that shingles",
      "start": 276.08,
      "duration": 4.64
    },
    {
      "text": "virus and that and the",
      "start": 278.32,
      "duration": 4.64
    },
    {
      "text": "simplex virus you're looking at knocking",
      "start": 280.72,
      "duration": 4.24
    },
    {
      "text": "those out so you can do a simplex",
      "start": 282.96,
      "duration": 4.0
    },
    {
      "text": "protocol you can be doing the shingles",
      "start": 284.96,
      "duration": 4.0
    },
    {
      "text": "protocol so that's the one you want and",
      "start": 286.96,
      "duration": 3.6
    },
    {
      "text": "cleanse the heal take it to your doctor",
      "start": 288.96,
      "duration": 2.88
    },
    {
      "text": "ask them what's right for you but the",
      "start": 290.56,
      "duration": 3.6
    },
    {
      "text": "shingles protocol so that's important",
      "start": 291.84,
      "duration": 5.52
    },
    {
      "text": "right there and and sometimes those you",
      "start": 294.16,
      "duration": 5.2
    },
    {
      "text": "know i'll tell you right now i've never",
      "start": 297.36,
      "duration": 3.52
    },
    {
      "text": "seen the needle move for trigeminal",
      "start": 299.36,
      "duration": 3.92
    },
    {
      "text": "neuralgia for anybody out there except",
      "start": 300.88,
      "duration": 4.96
    },
    {
      "text": "for medical medium protocols i've never",
      "start": 303.28,
      "duration": 4.88
    },
    {
      "text": "seen it move i mean i've talked to",
      "start": 305.84,
      "duration": 4.16
    },
    {
      "text": "hundreds of doctors for the last 35",
      "start": 308.16,
      "duration": 3.52
    },
    {
      "text": "years and trigeminal neuralgia is that",
      "start": 310.0,
      "duration": 3.36
    },
    {
      "text": "kind of thing that never budges unless",
      "start": 311.68,
      "duration": 3.28
    },
    {
      "text": "you do the right thing so there are",
      "start": 313.36,
      "duration": 3.839
    },
    {
      "text": "answers you got to stay with it you got",
      "start": 314.96,
      "duration": 5.04
    },
    {
      "text": "to you know learn how to chip away and",
      "start": 317.199,
      "duration": 5.201
    },
    {
      "text": "chip away until those viral that viral",
      "start": 320.0,
      "duration": 4.56
    },
    {
      "text": "inflammation is down and gone and when",
      "start": 322.4,
      "duration": 4.079
    },
    {
      "text": "it's gone all of a sudden you can chew",
      "start": 324.56,
      "duration": 3.919
    },
    {
      "text": "again oh my god i can chew again all of",
      "start": 326.479,
      "duration": 3.841
    },
    {
      "text": "a sudden you can start feeling better",
      "start": 328.479,
      "duration": 3.681
    },
    {
      "text": "what happens is",
      "start": 330.32,
      "duration": 3.76
    },
    {
      "text": "cranial nerves right here so cranial",
      "start": 332.16,
      "duration": 3.52
    },
    {
      "text": "nerves",
      "start": 334.08,
      "duration": 3.92
    },
    {
      "text": "the trigeminal nerve right that's your",
      "start": 335.68,
      "duration": 4.64
    },
    {
      "text": "cranial nerve so trigeminal neuralgia is",
      "start": 338.0,
      "duration": 5.039
    },
    {
      "text": "about an inflamed cranial nerve cranial",
      "start": 340.32,
      "duration": 4.879
    },
    {
      "text": "nerves are why people are sick with so",
      "start": 343.039,
      "duration": 3.681
    },
    {
      "text": "many different things",
      "start": 345.199,
      "duration": 3.121
    },
    {
      "text": "and this is just one thing right there",
      "start": 346.72,
      "duration": 2.64
    },
    {
      "text": "so",
      "start": 348.32,
      "duration": 2.64
    },
    {
      "text": "kimberly miller trying to get back onto",
      "start": 349.36,
      "duration": 3.52
    },
    {
      "text": "the mono cleanse",
      "start": 350.96,
      "duration": 3.36
    },
    {
      "text": "i totally get it it's not easy to get",
      "start": 352.88,
      "duration": 2.8
    },
    {
      "text": "back onto the mono cleanse but i'm",
      "start": 354.32,
      "duration": 2.719
    },
    {
      "text": "really proud of you for trying to do",
      "start": 355.68,
      "duration": 4.16
    },
    {
      "text": "that that's incredible right there um so",
      "start": 357.039,
      "duration": 4.321
    },
    {
      "text": "yeah you guys so let's talk a little bit",
      "start": 359.84,
      "duration": 3.52
    },
    {
      "text": "more about why we're sick just like",
      "start": 361.36,
      "duration": 3.6
    },
    {
      "text": "we're doing now and we'll keep on doing",
      "start": 363.36,
      "duration": 4.559
    },
    {
      "text": "that right there so",
      "start": 364.96,
      "duration": 5.359
    },
    {
      "text": "if you",
      "start": 367.919,
      "duration": 2.4
    },
    {
      "text": "if you're somebody that's been",
      "start": 370.8,
      "duration": 3.36
    },
    {
      "text": "struggling for a long time",
      "start": 372.08,
      "duration": 3.92
    },
    {
      "text": "you've been you've been trying to find",
      "start": 374.16,
      "duration": 3.68
    },
    {
      "text": "answers right",
      "start": 376.0,
      "duration": 4.319
    },
    {
      "text": "you want to know why you're sick and you",
      "start": 377.84,
      "duration": 4.24
    },
    {
      "text": "get answers and you get answers like",
      "start": 380.319,
      "duration": 3.44
    },
    {
      "text": "things like it's all in your gut or",
      "start": 382.08,
      "duration": 3.44
    },
    {
      "text": "something and that's not an answer i've",
      "start": 383.759,
      "duration": 3.361
    },
    {
      "text": "seen this so so many times with people",
      "start": 385.52,
      "duration": 3.04
    },
    {
      "text": "laurie says what causes a burning",
      "start": 387.12,
      "duration": 4.16
    },
    {
      "text": "sensation in the mouth when eating food",
      "start": 388.56,
      "duration": 4.88
    },
    {
      "text": "ebv or something else if i had a burning",
      "start": 391.28,
      "duration": 5.84
    },
    {
      "text": "sensation in my mouth okay",
      "start": 393.44,
      "duration": 5.36
    },
    {
      "text": "so if i had a burning sensation in my",
      "start": 397.12,
      "duration": 4.48
    },
    {
      "text": "mouth right",
      "start": 398.8,
      "duration": 2.8
    },
    {
      "text": "burning sensations i call it burning",
      "start": 401.759,
      "duration": 5.28
    },
    {
      "text": "tongue burning gums burning mouth right",
      "start": 403.52,
      "duration": 6.32
    },
    {
      "text": "that's that right there okay that's a",
      "start": 407.039,
      "duration": 5.041
    },
    {
      "text": "viral issue too so keep that in mind so",
      "start": 409.84,
      "duration": 3.759
    },
    {
      "text": "it's a viral issue when we go to the",
      "start": 412.08,
      "duration": 2.88
    },
    {
      "text": "doctors they don't know what burning",
      "start": 413.599,
      "duration": 3.521
    },
    {
      "text": "mouth burning tongue is they don't know",
      "start": 414.96,
      "duration": 3.84
    },
    {
      "text": "what burning cheeks are they don't know",
      "start": 417.12,
      "duration": 3.72
    },
    {
      "text": "what any of that is",
      "start": 418.8,
      "duration": 4.16
    },
    {
      "text": "and unless they're learning and they're",
      "start": 420.84,
      "duration": 3.56
    },
    {
      "text": "picking up medical medium information",
      "start": 422.96,
      "duration": 2.959
    },
    {
      "text": "because i've noticed that that that's",
      "start": 424.4,
      "duration": 3.04
    },
    {
      "text": "what's happening i noticed that the",
      "start": 425.919,
      "duration": 3.441
    },
    {
      "text": "clinics are taking mm info they've never",
      "start": 427.44,
      "duration": 2.72
    },
    {
      "text": "had",
      "start": 429.36,
      "duration": 2.559
    },
    {
      "text": "they're taking it right out of published",
      "start": 430.16,
      "duration": 3.039
    },
    {
      "text": "medical medium books and they're",
      "start": 431.919,
      "duration": 3.12
    },
    {
      "text": "starting to put it on their websites",
      "start": 433.199,
      "duration": 3.681
    },
    {
      "text": "like information that doesn't have a",
      "start": 435.039,
      "duration": 4.081
    },
    {
      "text": "study behind it but it came from",
      "start": 436.88,
      "duration": 4.4
    },
    {
      "text": "these books right so i noticed that",
      "start": 439.12,
      "duration": 4.56
    },
    {
      "text": "right now there's a big like thirst for",
      "start": 441.28,
      "duration": 4.24
    },
    {
      "text": "stealing information it's actually",
      "start": 443.68,
      "duration": 3.76
    },
    {
      "text": "hilarious but whatever",
      "start": 445.52,
      "duration": 4.079
    },
    {
      "text": "but what happens is when you go to the",
      "start": 447.44,
      "duration": 3.84
    },
    {
      "text": "best clinics and you tell them you've",
      "start": 449.599,
      "duration": 3.44
    },
    {
      "text": "got a burning tongue burning mouth",
      "start": 451.28,
      "duration": 3.28
    },
    {
      "text": "burning gums",
      "start": 453.039,
      "duration": 2.88
    },
    {
      "text": "and they'll just look at you like you're",
      "start": 454.56,
      "duration": 3.84
    },
    {
      "text": "crazy they won't know",
      "start": 455.919,
      "duration": 4.801
    },
    {
      "text": "they won't know that's also trigeminal",
      "start": 458.4,
      "duration": 5.04
    },
    {
      "text": "neuralgia and other cranial nerves that",
      "start": 460.72,
      "duration": 5.28
    },
    {
      "text": "cause the burning tongue burning face",
      "start": 463.44,
      "duration": 4.479
    },
    {
      "text": "you know burning face too burning face",
      "start": 466.0,
      "duration": 3.28
    },
    {
      "text": "burning cheeks",
      "start": 467.919,
      "duration": 4.0
    },
    {
      "text": "burning eyes optic nerves so the burning",
      "start": 469.28,
      "duration": 4.24
    },
    {
      "text": "eyes you feel like you got burning in",
      "start": 471.919,
      "duration": 3.441
    },
    {
      "text": "your forehead burning in back of your",
      "start": 473.52,
      "duration": 2.88
    },
    {
      "text": "eyes",
      "start": 475.36,
      "duration": 3.76
    },
    {
      "text": "all of that right that's all the cranial",
      "start": 476.4,
      "duration": 5.04
    },
    {
      "text": "nerves getting inflamed by viruses it",
      "start": 479.12,
      "duration": 3.759
    },
    {
      "text": "means people walk around with a lot of",
      "start": 481.44,
      "duration": 3.92
    },
    {
      "text": "ebv's shingles simplexes those are the",
      "start": 482.879,
      "duration": 4.32
    },
    {
      "text": "most common for that",
      "start": 485.36,
      "duration": 4.399
    },
    {
      "text": "right there and shingles is a big one",
      "start": 487.199,
      "duration": 4.481
    },
    {
      "text": "right there people don't know about the",
      "start": 489.759,
      "duration": 3.44
    },
    {
      "text": "shingles so cold white springs so maybe",
      "start": 491.68,
      "duration": 2.88
    },
    {
      "text": "you said burning of shingles yeah",
      "start": 493.199,
      "duration": 3.761
    },
    {
      "text": "definitely burning in joy clark i was",
      "start": 494.56,
      "duration": 4.16
    },
    {
      "text": "sick for 35 years of trigeminal",
      "start": 496.96,
      "duration": 4.4
    },
    {
      "text": "neuralgia with hope because i did not",
      "start": 498.72,
      "duration": 6.319
    },
    {
      "text": "have the mm information",
      "start": 501.36,
      "duration": 7.44
    },
    {
      "text": "i do not know how i survived now i am on",
      "start": 505.039,
      "duration": 8.081
    },
    {
      "text": "round 16 of the 369 cleanse yeah",
      "start": 508.8,
      "duration": 7.039
    },
    {
      "text": "zero fat is what moves the needle as",
      "start": 513.12,
      "duration": 4.96
    },
    {
      "text": "well as all the supplements when not on",
      "start": 515.839,
      "duration": 4.56
    },
    {
      "text": "the cleanse so trigeminal neuralgia is a",
      "start": 518.08,
      "duration": 4.56
    },
    {
      "text": "shingles problem so when i look at the",
      "start": 520.399,
      "duration": 4.0
    },
    {
      "text": "supplements i have right here right",
      "start": 522.64,
      "duration": 3.28
    },
    {
      "text": "these are the vimergy supplements it's",
      "start": 524.399,
      "duration": 3.521
    },
    {
      "text": "the best stuff out there so let me open",
      "start": 525.92,
      "duration": 3.12
    },
    {
      "text": "up cleanse the heal let's just hit",
      "start": 527.92,
      "duration": 2.88
    },
    {
      "text": "trigeminal neuralgia because people have",
      "start": 529.04,
      "duration": 3.04
    },
    {
      "text": "it and they don't even know do you guys",
      "start": 530.8,
      "duration": 2.24
    },
    {
      "text": "know that",
      "start": 532.08,
      "duration": 2.4
    },
    {
      "text": "they have jaw pain they don't know it's",
      "start": 533.04,
      "duration": 3.52
    },
    {
      "text": "trigeminal neuralgia they have burning",
      "start": 534.48,
      "duration": 3.84
    },
    {
      "text": "gum burning gum they have a funny",
      "start": 536.56,
      "duration": 2.959
    },
    {
      "text": "feeling on the tongue they don't know",
      "start": 538.32,
      "duration": 3.04
    },
    {
      "text": "it's trigeminal neuralgia",
      "start": 539.519,
      "duration": 3.041
    },
    {
      "text": "they don't know it's their cranial",
      "start": 541.36,
      "duration": 3.52
    },
    {
      "text": "nerves that's what happens right",
      "start": 542.56,
      "duration": 3.76
    },
    {
      "text": "so i'm gonna look for the shingles",
      "start": 544.88,
      "duration": 3.6
    },
    {
      "text": "section right here real quick see if i",
      "start": 546.32,
      "duration": 4.639
    },
    {
      "text": "can find it for you guys right",
      "start": 548.48,
      "duration": 4.16
    },
    {
      "text": "and",
      "start": 550.959,
      "duration": 3.201
    },
    {
      "text": "so it's important here it is a single",
      "start": 552.64,
      "duration": 2.879
    },
    {
      "text": "section right here so what's in the",
      "start": 554.16,
      "duration": 2.96
    },
    {
      "text": "protocol okay",
      "start": 555.519,
      "duration": 2.961
    },
    {
      "text": "got a few different things right here",
      "start": 557.12,
      "duration": 3.36
    },
    {
      "text": "we've got cat's claw so that's in the",
      "start": 558.48,
      "duration": 3.76
    },
    {
      "text": "protocol right here so the best cat",
      "start": 560.48,
      "duration": 3.919
    },
    {
      "text": "squad out there is the",
      "start": 562.24,
      "duration": 4.08
    },
    {
      "text": "is the vimergy cat's claw so that's it",
      "start": 564.399,
      "duration": 4.401
    },
    {
      "text": "right there okay so cats claw that's the",
      "start": 566.32,
      "duration": 6.24
    },
    {
      "text": "bimmer g1 vs victor i m e r g y dot com",
      "start": 568.8,
      "duration": 5.599
    },
    {
      "text": "i'm not sponsored it's the best stuff",
      "start": 572.56,
      "duration": 2.8
    },
    {
      "text": "out there",
      "start": 574.399,
      "duration": 4.641
    },
    {
      "text": "when you use cat's claw for viral issues",
      "start": 575.36,
      "duration": 5.52
    },
    {
      "text": "it could be anything like the restless",
      "start": 579.04,
      "duration": 4.239
    },
    {
      "text": "leg syndrome it could be like tingles",
      "start": 580.88,
      "duration": 4.32
    },
    {
      "text": "and numbness it could be neurological",
      "start": 583.279,
      "duration": 4.481
    },
    {
      "text": "fatigue where you're fatigued you guys",
      "start": 585.2,
      "duration": 4.16
    },
    {
      "text": "right you don't have an explanation to",
      "start": 587.76,
      "duration": 3.36
    },
    {
      "text": "why you're fatigued it could be ticks",
      "start": 589.36,
      "duration": 4.32
    },
    {
      "text": "and spasms and all kinds of different",
      "start": 591.12,
      "duration": 4.719
    },
    {
      "text": "you know um you know feeling creepy",
      "start": 593.68,
      "duration": 3.839
    },
    {
      "text": "crawlies on the skin but there's nothing",
      "start": 595.839,
      "duration": 3.44
    },
    {
      "text": "on your skin and you go to the doctors",
      "start": 597.519,
      "duration": 3.76
    },
    {
      "text": "all these neurological symptoms cat's",
      "start": 599.279,
      "duration": 3.921
    },
    {
      "text": "claws critical neurological lyme",
      "start": 601.279,
      "duration": 3.521
    },
    {
      "text": "multiple sclerosis",
      "start": 603.2,
      "duration": 4.319
    },
    {
      "text": "als and forget those forget those labels",
      "start": 604.8,
      "duration": 4.64
    },
    {
      "text": "you just don't know why you don't feel",
      "start": 607.519,
      "duration": 2.961
    },
    {
      "text": "good",
      "start": 609.44,
      "duration": 2.8
    },
    {
      "text": "and it's a neurological symptom cat's",
      "start": 610.48,
      "duration": 4.0
    },
    {
      "text": "claw is critical so that's a cat's claw",
      "start": 612.24,
      "duration": 3.2
    },
    {
      "text": "right there so if you look at the",
      "start": 614.48,
      "duration": 3.84
    },
    {
      "text": "shingles right here okay section the",
      "start": 615.44,
      "duration": 5.519
    },
    {
      "text": "shingles virus is the true cause of",
      "start": 618.32,
      "duration": 5.519
    },
    {
      "text": "trigeminal neuralgia frozen shoulder how",
      "start": 620.959,
      "duration": 4.241
    },
    {
      "text": "many of you guys ever had frozen",
      "start": 623.839,
      "duration": 4.481
    },
    {
      "text": "shoulder right ulcerative colitis how",
      "start": 625.2,
      "duration": 5.04
    },
    {
      "text": "many of you guys had ulcerative colitis",
      "start": 628.32,
      "duration": 4.56
    },
    {
      "text": "and many cases of neck pain jaw pain gum",
      "start": 630.24,
      "duration": 5.12
    },
    {
      "text": "and tooth pain tongue pain burning",
      "start": 632.88,
      "duration": 4.16
    },
    {
      "text": "sensations in the mouth burning",
      "start": 635.36,
      "duration": 3.919
    },
    {
      "text": "sensations on your skin",
      "start": 637.04,
      "duration": 4.799
    },
    {
      "text": "pain in the back of your head right the",
      "start": 639.279,
      "duration": 5.361
    },
    {
      "text": "pain in your back your head right",
      "start": 641.839,
      "duration": 5.041
    },
    {
      "text": "that too okay",
      "start": 644.64,
      "duration": 5.04
    },
    {
      "text": "migraine related pain mystery sciatic",
      "start": 646.88,
      "duration": 4.959
    },
    {
      "text": "pain your back's killing you you can't",
      "start": 649.68,
      "duration": 4.399
    },
    {
      "text": "sit on your wallet you got the sciatic",
      "start": 651.839,
      "duration": 3.761
    },
    {
      "text": "nerve pain in the back that's the",
      "start": 654.079,
      "duration": 3.44
    },
    {
      "text": "shingles right there okay",
      "start": 655.6,
      "duration": 4.16
    },
    {
      "text": "the shingles infection can happen with",
      "start": 657.519,
      "duration": 3.76
    },
    {
      "text": "no rashes",
      "start": 659.76,
      "duration": 3.199
    },
    {
      "text": "so what i love about this here's the",
      "start": 661.279,
      "duration": 3.361
    },
    {
      "text": "cat's claw right here it says two",
      "start": 662.959,
      "duration": 5.041
    },
    {
      "text": "dropper fulls twice a day in the book if",
      "start": 664.64,
      "duration": 5.199
    },
    {
      "text": "you're dealing with anything ask your",
      "start": 668.0,
      "duration": 3.36
    },
    {
      "text": "doctor it's right for you but that's the",
      "start": 669.839,
      "duration": 3.361
    },
    {
      "text": "cleanse the heel book it's a life-saving",
      "start": 671.36,
      "duration": 3.599
    },
    {
      "text": "book for so many people out there in the",
      "start": 673.2,
      "duration": 2.56
    },
    {
      "text": "world",
      "start": 674.959,
      "duration": 2.641
    },
    {
      "text": "two dropper fulls twice a day of cats",
      "start": 675.76,
      "duration": 4.0
    },
    {
      "text": "claw i'm not sponsored i don't own the",
      "start": 677.6,
      "duration": 4.4
    },
    {
      "text": "company i love when people are like oh",
      "start": 679.76,
      "duration": 4.96
    },
    {
      "text": "he must be the owner no okay i'm not",
      "start": 682.0,
      "duration": 5.12
    },
    {
      "text": "sponsored i don't own the company i do",
      "start": 684.72,
      "duration": 5.44
    },
    {
      "text": "work with wyman's and i'm proud of it",
      "start": 687.12,
      "duration": 5.839
    },
    {
      "text": "wyman's shop wyman's okay",
      "start": 690.16,
      "duration": 4.88
    },
    {
      "text": "right shop.wymans.com",
      "start": 692.959,
      "duration": 3.761
    },
    {
      "text": "right that's the wild blueberry juice",
      "start": 695.04,
      "duration": 3.52
    },
    {
      "text": "which is just incredible i'm going to",
      "start": 696.72,
      "duration": 3.44
    },
    {
      "text": "drink some in a little bit because i'm",
      "start": 698.56,
      "duration": 3.6
    },
    {
      "text": "actually thirsty i just did the amazon",
      "start": 700.16,
      "duration": 3.44
    },
    {
      "text": "live i want to have some some wild",
      "start": 702.16,
      "duration": 3.44
    },
    {
      "text": "blueberry juice i do work with wyman's",
      "start": 703.6,
      "duration": 4.0
    },
    {
      "text": "to make sure that that stuff sticks",
      "start": 705.6,
      "duration": 3.679
    },
    {
      "text": "around i mean what they have to do in",
      "start": 707.6,
      "duration": 3.76
    },
    {
      "text": "order to get that in a bottle is",
      "start": 709.279,
      "duration": 4.161
    },
    {
      "text": "unbelievable anyway",
      "start": 711.36,
      "duration": 4.479
    },
    {
      "text": "but i i don't i'm not sponsored by",
      "start": 713.44,
      "duration": 4.8
    },
    {
      "text": "vimergy but the stuff is incredible i",
      "start": 715.839,
      "duration": 3.841
    },
    {
      "text": "recommend the friends family so that's",
      "start": 718.24,
      "duration": 4.159
    },
    {
      "text": "the cats claw very important critical",
      "start": 719.68,
      "duration": 5.12
    },
    {
      "text": "when it comes down to healing",
      "start": 722.399,
      "duration": 4.481
    },
    {
      "text": "okay another thing for trigeminal",
      "start": 724.8,
      "duration": 3.52
    },
    {
      "text": "neuralgia i'm looking at really quick",
      "start": 726.88,
      "duration": 3.84
    },
    {
      "text": "here lemon balm it says four dropper",
      "start": 728.32,
      "duration": 6.8
    },
    {
      "text": "fulls three times a day four dropper",
      "start": 730.72,
      "duration": 6.4
    },
    {
      "text": "fulls three times a day now remember",
      "start": 735.12,
      "duration": 4.8
    },
    {
      "text": "this is for shingles frozen shoulder",
      "start": 737.12,
      "duration": 5.279
    },
    {
      "text": "ulcerative colitis many cases of neck",
      "start": 739.92,
      "duration": 4.8
    },
    {
      "text": "pain jaw pain gum pain tooth pain tongue",
      "start": 742.399,
      "duration": 4.081
    },
    {
      "text": "pain burning sensations inside the mouth",
      "start": 744.72,
      "duration": 4.08
    },
    {
      "text": "burning sensations on the skin pain in",
      "start": 746.48,
      "duration": 4.08
    },
    {
      "text": "the back of the head migraine related",
      "start": 748.8,
      "duration": 4.96
    },
    {
      "text": "pain sciatica pain mystery lower back",
      "start": 750.56,
      "duration": 6.48
    },
    {
      "text": "pain how many guys have that neuropathy",
      "start": 753.76,
      "duration": 4.72
    },
    {
      "text": "and even neuropathy",
      "start": 757.04,
      "duration": 2.72
    },
    {
      "text": "okay",
      "start": 758.48,
      "duration": 3.359
    },
    {
      "text": "and so what you do is",
      "start": 759.76,
      "duration": 5.28
    },
    {
      "text": "you can read the chapter okay and make",
      "start": 761.839,
      "duration": 4.881
    },
    {
      "text": "sure you read the supplement protocol",
      "start": 765.04,
      "duration": 3.52
    },
    {
      "text": "chapter before you start anything so",
      "start": 766.72,
      "duration": 3.679
    },
    {
      "text": "make sure you get cleansed to heal get",
      "start": 768.56,
      "duration": 4.079
    },
    {
      "text": "it free at the library all right it",
      "start": 770.399,
      "duration": 4.401
    },
    {
      "text": "costs more to print it if you go to you",
      "start": 772.639,
      "duration": 4.081
    },
    {
      "text": "go to amazon.com it's so cheap on",
      "start": 774.8,
      "duration": 5.039
    },
    {
      "text": "amazon.com right now it's 16.99 51 off",
      "start": 776.72,
      "duration": 4.239
    },
    {
      "text": "you guys",
      "start": 779.839,
      "duration": 2.721
    },
    {
      "text": "you guys have to understand something",
      "start": 780.959,
      "duration": 2.721
    },
    {
      "text": "right",
      "start": 782.56,
      "duration": 3.12
    },
    {
      "text": "i'm really really",
      "start": 783.68,
      "duration": 4.24
    },
    {
      "text": "like i get hopped up and i get",
      "start": 785.68,
      "duration": 4.64
    },
    {
      "text": "passionate about the symptoms and",
      "start": 787.92,
      "duration": 3.84
    },
    {
      "text": "conditions",
      "start": 790.32,
      "duration": 3.6
    },
    {
      "text": "because all i do",
      "start": 791.76,
      "duration": 3.6
    },
    {
      "text": "is feel",
      "start": 793.92,
      "duration": 3.919
    },
    {
      "text": "someone suffering someone's suffering",
      "start": 795.36,
      "duration": 3.599
    },
    {
      "text": "bad",
      "start": 797.839,
      "duration": 3.841
    },
    {
      "text": "no one gets it unless they had frozen",
      "start": 798.959,
      "duration": 4.56
    },
    {
      "text": "shoulder and they couldn't move half",
      "start": 801.68,
      "duration": 4.08
    },
    {
      "text": "their body for about a year no one gets",
      "start": 803.519,
      "duration": 3.041
    },
    {
      "text": "it",
      "start": 805.76,
      "duration": 2.8
    },
    {
      "text": "unless they're the ones that got the",
      "start": 806.56,
      "duration": 3.2
    },
    {
      "text": "burning skin",
      "start": 808.56,
      "duration": 2.88
    },
    {
      "text": "and the burning face and couldn't sleep",
      "start": 809.76,
      "duration": 4.8
    },
    {
      "text": "and had to take all these crazy drugs",
      "start": 811.44,
      "duration": 4.88
    },
    {
      "text": "crazy prescription drugs because they",
      "start": 814.56,
      "duration": 3.44
    },
    {
      "text": "can't even sleep their pain their their",
      "start": 816.32,
      "duration": 3.759
    },
    {
      "text": "jaw's on fire",
      "start": 818.0,
      "duration": 4.0
    },
    {
      "text": "it's these things that matter it's this",
      "start": 820.079,
      "duration": 4.241
    },
    {
      "text": "it's people suffering it's their chronic",
      "start": 822.0,
      "duration": 4.72
    },
    {
      "text": "symptoms that take them down and make",
      "start": 824.32,
      "duration": 4.16
    },
    {
      "text": "them feel like they're they're hopeless",
      "start": 826.72,
      "duration": 2.799
    },
    {
      "text": "it makes them feel like they're",
      "start": 828.48,
      "duration": 3.12
    },
    {
      "text": "worthless i've seen so many people",
      "start": 829.519,
      "duration": 5.201
    },
    {
      "text": "suffer when they're so sick for so long",
      "start": 831.6,
      "duration": 5.2
    },
    {
      "text": "and so what i do is i'm like you know",
      "start": 834.72,
      "duration": 4.239
    },
    {
      "text": "what who can i help today",
      "start": 836.8,
      "duration": 5.36
    },
    {
      "text": "like who can i help is there someone out",
      "start": 838.959,
      "duration": 5.201
    },
    {
      "text": "there that doesn't even know and realize",
      "start": 842.16,
      "duration": 4.08
    },
    {
      "text": "it and they just came on here like who",
      "start": 844.16,
      "duration": 4.96
    },
    {
      "text": "is this guy and i'm saying he there are",
      "start": 846.24,
      "duration": 4.24
    },
    {
      "text": "answers",
      "start": 849.12,
      "duration": 3.6
    },
    {
      "text": "there are answers get it free at the",
      "start": 850.48,
      "duration": 4.64
    },
    {
      "text": "library i don't care",
      "start": 852.72,
      "duration": 4.479
    },
    {
      "text": "it doesn't matter yeah you can get an",
      "start": 855.12,
      "duration": 4.719
    },
    {
      "text": "amazon dirt cheap cost more to print it",
      "start": 857.199,
      "duration": 4.64
    },
    {
      "text": "in from what they sell for but get it",
      "start": 859.839,
      "duration": 4.401
    },
    {
      "text": "for eat the library if you need to",
      "start": 861.839,
      "duration": 4.881
    },
    {
      "text": "learn how to take cat's cloth the right",
      "start": 864.24,
      "duration": 5.039
    },
    {
      "text": "kind learn how to get zinc in you",
      "start": 866.72,
      "duration": 4.4
    },
    {
      "text": "because people are so sick with all",
      "start": 869.279,
      "duration": 3.601
    },
    {
      "text": "these symptoms and there are answers and",
      "start": 871.12,
      "duration": 4.56
    },
    {
      "text": "ways learn how to do the right cleanse",
      "start": 872.88,
      "duration": 3.759
    },
    {
      "text": "man",
      "start": 875.68,
      "duration": 3.2
    },
    {
      "text": "if people only knew who were suffering",
      "start": 876.639,
      "duration": 5.121
    },
    {
      "text": "for five years you do the 369 what it",
      "start": 878.88,
      "duration": 5.519
    },
    {
      "text": "can do what brand is that for the lemon",
      "start": 881.76,
      "duration": 3.759
    },
    {
      "text": "balm",
      "start": 884.399,
      "duration": 3.12
    },
    {
      "text": "lemon balm is vimergy vicky so it's",
      "start": 885.519,
      "duration": 4.481
    },
    {
      "text": "vimergy v is in victor i am as in mary",
      "start": 887.519,
      "duration": 5.601
    },
    {
      "text": "e-r-g-y dot-com they're salt of the",
      "start": 890.0,
      "duration": 5.44
    },
    {
      "text": "earth i've become friends with them over",
      "start": 893.12,
      "duration": 5.2
    },
    {
      "text": "the years because they keep the standard",
      "start": 895.44,
      "duration": 5.6
    },
    {
      "text": "so high with the products every time i",
      "start": 898.32,
      "duration": 5.04
    },
    {
      "text": "i'm friends with a dozen supplement",
      "start": 901.04,
      "duration": 4.4
    },
    {
      "text": "companies out there right",
      "start": 903.36,
      "duration": 4.56
    },
    {
      "text": "because i try to build a relationship",
      "start": 905.44,
      "duration": 4.56
    },
    {
      "text": "and i build a relationship with them and",
      "start": 907.92,
      "duration": 4.0
    },
    {
      "text": "they say they're going to keep the stuff",
      "start": 910.0,
      "duration": 3.68
    },
    {
      "text": "really high quality and then they",
      "start": 911.92,
      "duration": 3.84
    },
    {
      "text": "totally screw me over and and and all of",
      "start": 913.68,
      "duration": 3.36
    },
    {
      "text": "a sudden they'll look at their bottle",
      "start": 915.76,
      "duration": 2.879
    },
    {
      "text": "one day and i'm like are you kidding",
      "start": 917.04,
      "duration": 3.2
    },
    {
      "text": "there why is there citric acid in here",
      "start": 918.639,
      "duration": 3.921
    },
    {
      "text": "so i call them up not vimergy but other",
      "start": 920.24,
      "duration": 4.159
    },
    {
      "text": "companies i'll call them up and be look",
      "start": 922.56,
      "duration": 4.16
    },
    {
      "text": "i thought we were had a i thought we had",
      "start": 924.399,
      "duration": 4.0
    },
    {
      "text": "some like a friendship i thought you",
      "start": 926.72,
      "duration": 3.52
    },
    {
      "text": "were on the same page we want to keep",
      "start": 928.399,
      "duration": 3.761
    },
    {
      "text": "this stuff clean for people and they're",
      "start": 930.24,
      "duration": 4.64
    },
    {
      "text": "like anthony sorry man but you know what",
      "start": 932.16,
      "duration": 4.799
    },
    {
      "text": "uh you're not the owner of this company",
      "start": 934.88,
      "duration": 4.639
    },
    {
      "text": "and we do what we want and and we're",
      "start": 936.959,
      "duration": 4.88
    },
    {
      "text": "gonna make our spirulina the way we",
      "start": 939.519,
      "duration": 4.401
    },
    {
      "text": "wanna make it and we're gonna make our",
      "start": 941.839,
      "duration": 3.761
    },
    {
      "text": "whatever it is the way we wanna make it",
      "start": 943.92,
      "duration": 3.2
    },
    {
      "text": "and you can't you we're not gonna have",
      "start": 945.6,
      "duration": 3.359
    },
    {
      "text": "you and your people who are sick like",
      "start": 947.12,
      "duration": 3.76
    },
    {
      "text": "tell us what to do and clean clean",
      "start": 948.959,
      "duration": 3.761
    },
    {
      "text": "supplements and stuff and that's what",
      "start": 950.88,
      "duration": 3.68
    },
    {
      "text": "happens i try to build relationships so",
      "start": 952.72,
      "duration": 3.76
    },
    {
      "text": "i could have communication i just",
      "start": 954.56,
      "duration": 3.839
    },
    {
      "text": "reached out to some other company that",
      "start": 956.48,
      "duration": 3.359
    },
    {
      "text": "that i thought i had communication with",
      "start": 958.399,
      "duration": 3.44
    },
    {
      "text": "and i don't have communication with it's",
      "start": 959.839,
      "duration": 3.44
    },
    {
      "text": "crazy and",
      "start": 961.839,
      "duration": 3.68
    },
    {
      "text": "and they're just like no we changed our",
      "start": 963.279,
      "duration": 3.68
    },
    {
      "text": "thing and what i can tell you is this",
      "start": 965.519,
      "duration": 3.12
    },
    {
      "text": "with vimeracy",
      "start": 966.959,
      "duration": 3.841
    },
    {
      "text": "they don't change",
      "start": 968.639,
      "duration": 4.721
    },
    {
      "text": "their quality standards are higher and",
      "start": 970.8,
      "duration": 4.24
    },
    {
      "text": "higher to the point where nothing on the",
      "start": 973.36,
      "duration": 3.52
    },
    {
      "text": "planet earth can touch their they're",
      "start": 975.04,
      "duration": 3.28
    },
    {
      "text": "like standard",
      "start": 976.88,
      "duration": 3.519
    },
    {
      "text": "it's just incredible anyway",
      "start": 978.32,
      "duration": 3.6
    },
    {
      "text": "all this stuff matters when you're",
      "start": 980.399,
      "duration": 4.56
    },
    {
      "text": "healing you can take a garbage zinc",
      "start": 981.92,
      "duration": 4.719
    },
    {
      "text": "and never heal",
      "start": 984.959,
      "duration": 4.24
    },
    {
      "text": "you can take a bottom of the barrel",
      "start": 986.639,
      "duration": 6.32
    },
    {
      "text": "junkies ink and never ever heal",
      "start": 989.199,
      "duration": 6.08
    },
    {
      "text": "i've seen this happen out there it's",
      "start": 992.959,
      "duration": 4.56
    },
    {
      "text": "like there is a way to heal with the",
      "start": 995.279,
      "duration": 5.281
    },
    {
      "text": "right stuff there just is and",
      "start": 997.519,
      "duration": 5.68
    },
    {
      "text": "information critical first michelle l",
      "start": 1000.56,
      "duration": 4.56
    },
    {
      "text": "michelle oh hey",
      "start": 1003.199,
      "duration": 4.08
    },
    {
      "text": "no one told me what the burning pain was",
      "start": 1005.12,
      "duration": 5.279
    },
    {
      "text": "and i asked so many times say w",
      "start": 1007.279,
      "duration": 5.201
    },
    {
      "text": "and that's how it is out there so",
      "start": 1010.399,
      "duration": 4.081
    },
    {
      "text": "answers are really important you guys",
      "start": 1012.48,
      "duration": 3.68
    },
    {
      "text": "and really important so let's talk about",
      "start": 1014.48,
      "duration": 3.52
    },
    {
      "text": "some other stuff too right",
      "start": 1016.16,
      "duration": 4.08
    },
    {
      "text": "i cannot find wyman's cat's claw i had",
      "start": 1018.0,
      "duration": 4.32
    },
    {
      "text": "jingles no way it's wyman's blueberry",
      "start": 1020.24,
      "duration": 3.76
    },
    {
      "text": "juice they got the wild blueberry juice",
      "start": 1022.32,
      "duration": 4.239
    },
    {
      "text": "right the cat's claw is vimergy margaret",
      "start": 1024.0,
      "duration": 5.199
    },
    {
      "text": "so it's v as in victor i-m-e-r-g-y",
      "start": 1026.559,
      "duration": 4.081
    },
    {
      "text": "lorraine l good to see you i just saw",
      "start": 1029.199,
      "duration": 3.76
    },
    {
      "text": "your comment fly up right there",
      "start": 1030.64,
      "duration": 3.84
    },
    {
      "text": "it's the the wyman's is the wild",
      "start": 1032.959,
      "duration": 3.12
    },
    {
      "text": "blueberry juice now i am working with",
      "start": 1034.48,
      "duration": 3.68
    },
    {
      "text": "these guys you guys full disclosure on",
      "start": 1036.079,
      "duration": 4.801
    },
    {
      "text": "that i am working with these guys i told",
      "start": 1038.16,
      "duration": 4.24
    },
    {
      "text": "you that since the first day i showed",
      "start": 1040.88,
      "duration": 3.76
    },
    {
      "text": "you the wyman's juice okay",
      "start": 1042.4,
      "duration": 6.08
    },
    {
      "text": "and and what it is is they need my help",
      "start": 1044.64,
      "duration": 5.6
    },
    {
      "text": "to make sure that because they're",
      "start": 1048.48,
      "duration": 4.16
    },
    {
      "text": "killing themselves to actually",
      "start": 1050.24,
      "duration": 4.4
    },
    {
      "text": "harvest these out of the field and press",
      "start": 1052.64,
      "duration": 2.8
    },
    {
      "text": "them",
      "start": 1054.64,
      "duration": 2.72
    },
    {
      "text": "throw them in a press",
      "start": 1055.44,
      "duration": 3.92
    },
    {
      "text": "and press it for us like and i'm like",
      "start": 1057.36,
      "duration": 4.559
    },
    {
      "text": "i'm on board i will do anything to make",
      "start": 1059.36,
      "duration": 4.72
    },
    {
      "text": "sure people know about that",
      "start": 1061.919,
      "duration": 4.801
    },
    {
      "text": "but you guys know that right um",
      "start": 1064.08,
      "duration": 4.16
    },
    {
      "text": "vertigo let's talk about dizziness and",
      "start": 1066.72,
      "duration": 3.36
    },
    {
      "text": "virgo michelle lewis let's go into that",
      "start": 1068.24,
      "duration": 4.96
    },
    {
      "text": "a little bit cranial nerves",
      "start": 1070.08,
      "duration": 5.36
    },
    {
      "text": "vagus nerves",
      "start": 1073.2,
      "duration": 4.88
    },
    {
      "text": "if you don't have if your doctor rules",
      "start": 1075.44,
      "duration": 5.84
    },
    {
      "text": "out a big old brain tumor right they",
      "start": 1078.08,
      "duration": 5.599
    },
    {
      "text": "roll out you get they do the cat scans",
      "start": 1081.28,
      "duration": 4.399
    },
    {
      "text": "they do the mris they don't see a big",
      "start": 1083.679,
      "duration": 3.681
    },
    {
      "text": "brain tumor they don't see something",
      "start": 1085.679,
      "duration": 3.841
    },
    {
      "text": "really in the way they're like we don't",
      "start": 1087.36,
      "duration": 4.319
    },
    {
      "text": "know why you can't we don't know why",
      "start": 1089.52,
      "duration": 4.08
    },
    {
      "text": "you're walking around like this",
      "start": 1091.679,
      "duration": 3.521
    },
    {
      "text": "we don't know why you're walking around",
      "start": 1093.6,
      "duration": 3.6
    },
    {
      "text": "like that as you're trying to get to the",
      "start": 1095.2,
      "duration": 4.16
    },
    {
      "text": "doctor's office or your head's feeling",
      "start": 1097.2,
      "duration": 4.32
    },
    {
      "text": "like it's spinning like this like that",
      "start": 1099.36,
      "duration": 3.04
    },
    {
      "text": "you know",
      "start": 1101.52,
      "duration": 1.6
    },
    {
      "text": "and",
      "start": 1102.4,
      "duration": 2.399
    },
    {
      "text": "the vertigo or you just feel like you're",
      "start": 1103.12,
      "duration": 3.52
    },
    {
      "text": "on a boat feel like you're on a boat",
      "start": 1104.799,
      "duration": 4.321
    },
    {
      "text": "you're like and what happens is those",
      "start": 1106.64,
      "duration": 4.159
    },
    {
      "text": "are vagus nerves",
      "start": 1109.12,
      "duration": 4.48
    },
    {
      "text": "cranial nerves right there",
      "start": 1110.799,
      "duration": 4.801
    },
    {
      "text": "they're inflamed",
      "start": 1113.6,
      "duration": 4.4
    },
    {
      "text": "that's what i tell people in my family",
      "start": 1115.6,
      "duration": 4.56
    },
    {
      "text": "or my friends that you know reach out",
      "start": 1118.0,
      "duration": 3.679
    },
    {
      "text": "after 20 years and they're like i got",
      "start": 1120.16,
      "duration": 3.519
    },
    {
      "text": "this vertigo",
      "start": 1121.679,
      "duration": 4.24
    },
    {
      "text": "i hate to bother you aw but i just need",
      "start": 1123.679,
      "duration": 5.041
    },
    {
      "text": "a couple of pointers i'm like dude have",
      "start": 1125.919,
      "duration": 5.361
    },
    {
      "text": "you looked at the medical medium book",
      "start": 1128.72,
      "duration": 5.44
    },
    {
      "text": "and got the vertigo information right",
      "start": 1131.28,
      "duration": 4.399
    },
    {
      "text": "doctors reach out to me like what do i",
      "start": 1134.16,
      "duration": 4.08
    },
    {
      "text": "do my patients that have vertigo a.w",
      "start": 1135.679,
      "duration": 4.801
    },
    {
      "text": "and so you got to get the vagus nerve",
      "start": 1138.24,
      "duration": 5.52
    },
    {
      "text": "inflammation down that's the key with",
      "start": 1140.48,
      "duration": 6.079
    },
    {
      "text": "vertigo this is alive right now a quick",
      "start": 1143.76,
      "duration": 5.12
    },
    {
      "text": "live on look there are answers there are",
      "start": 1146.559,
      "duration": 5.441
    },
    {
      "text": "true causes viral issues cause vertigo",
      "start": 1148.88,
      "duration": 5.36
    },
    {
      "text": "inflamed vagus nerves caused by",
      "start": 1152.0,
      "duration": 4.32
    },
    {
      "text": "epstein-barr that's the reason for",
      "start": 1154.24,
      "duration": 4.72
    },
    {
      "text": "vertigo right there",
      "start": 1156.32,
      "duration": 3.44
    },
    {
      "text": "so",
      "start": 1158.96,
      "duration": 3.28
    },
    {
      "text": "i have healed so much with this info",
      "start": 1159.76,
      "duration": 4.4
    },
    {
      "text": "still have more to go but the more i",
      "start": 1162.24,
      "duration": 4.48
    },
    {
      "text": "stay true the better i get wondering",
      "start": 1164.16,
      "duration": 5.36
    },
    {
      "text": "wondering right wishing right",
      "start": 1166.72,
      "duration": 4.0
    },
    {
      "text": "it's really cool handle wondering",
      "start": 1169.52,
      "duration": 2.48
    },
    {
      "text": "wishing",
      "start": 1170.72,
      "duration": 3.44
    },
    {
      "text": "so i got to tell you something right",
      "start": 1172.0,
      "duration": 3.919
    },
    {
      "text": "that's the key",
      "start": 1174.16,
      "duration": 2.72
    },
    {
      "text": "it's",
      "start": 1175.919,
      "duration": 3.681
    },
    {
      "text": "it's how far you go it's what you do",
      "start": 1176.88,
      "duration": 4.96
    },
    {
      "text": "it's how much you do it's there you can",
      "start": 1179.6,
      "duration": 3.68
    },
    {
      "text": "take a little bit of the time but you",
      "start": 1181.84,
      "duration": 3.44
    },
    {
      "text": "can get there you guys you can get there",
      "start": 1183.28,
      "duration": 4.16
    },
    {
      "text": "you guys on tick tock check out cleanse",
      "start": 1185.28,
      "duration": 3.519
    },
    {
      "text": "the heel you won't be sorry it's a",
      "start": 1187.44,
      "duration": 2.96
    },
    {
      "text": "medical textbook that's saving lives",
      "start": 1188.799,
      "duration": 3.76
    },
    {
      "text": "around the world millions of copies sold",
      "start": 1190.4,
      "duration": 3.68
    },
    {
      "text": "around the world",
      "start": 1192.559,
      "duration": 3.12
    },
    {
      "text": "the medical medium book series is the",
      "start": 1194.08,
      "duration": 3.76
    },
    {
      "text": "most popular health series in the world",
      "start": 1195.679,
      "duration": 4.081
    },
    {
      "text": "seven years running",
      "start": 1197.84,
      "duration": 4.16
    },
    {
      "text": "that's what my publisher tells me",
      "start": 1199.76,
      "duration": 3.2
    },
    {
      "text": "okay",
      "start": 1202.0,
      "duration": 2.64
    },
    {
      "text": "and there's a reason",
      "start": 1202.96,
      "duration": 4.88
    },
    {
      "text": "no marketing no marketing",
      "start": 1204.64,
      "duration": 4.88
    },
    {
      "text": "no millions of dollars of marketing",
      "start": 1207.84,
      "duration": 3.52
    },
    {
      "text": "money going in like the other books out",
      "start": 1209.52,
      "duration": 2.72
    },
    {
      "text": "there",
      "start": 1211.36,
      "duration": 2.96
    },
    {
      "text": "none of that it's because someone healed",
      "start": 1212.24,
      "duration": 3.84
    },
    {
      "text": "and someone healed and someone healed",
      "start": 1214.32,
      "duration": 4.52
    },
    {
      "text": "and someone healed and blah blah",
      "start": 1216.08,
      "duration": 6.8
    },
    {
      "text": "blah and they learned not to eat eggs",
      "start": 1218.84,
      "duration": 6.12
    },
    {
      "text": "they learned you know",
      "start": 1222.88,
      "duration": 6.64
    },
    {
      "text": "i'm going to ig going ig i'm going ig",
      "start": 1224.96,
      "duration": 7.12
    },
    {
      "text": "honey eggs eggs i want my eggs eat my",
      "start": 1229.52,
      "duration": 4.639
    },
    {
      "text": "eggs eat my eggs eat my eggs eggs eggs",
      "start": 1232.08,
      "duration": 4.079
    },
    {
      "text": "eggs eggs over easy eggs scrambled eggs",
      "start": 1234.159,
      "duration": 3.201
    },
    {
      "text": "scrambled eggs omelettes omelets",
      "start": 1236.159,
      "duration": 2.64
    },
    {
      "text": "scrambled eggs omelets almost protein",
      "start": 1237.36,
      "duration": 3.52
    },
    {
      "text": "robot protein robot no egg robot egg",
      "start": 1238.799,
      "duration": 4.24
    },
    {
      "text": "robot egg robot apple cider vinegar all",
      "start": 1240.88,
      "duration": 3.52
    },
    {
      "text": "right apple cider vinegar apple cider",
      "start": 1243.039,
      "duration": 2.88
    },
    {
      "text": "vinegar eggs eggs can i have levels",
      "start": 1244.4,
      "duration": 3.6
    },
    {
      "text": "everywhere my eggs eggs i gotta go to i",
      "start": 1245.919,
      "duration": 5.361
    },
    {
      "text": "j go to rj i've got energy",
      "start": 1248.0,
      "duration": 5.52
    },
    {
      "text": "i'm putting tick tock back on try doing",
      "start": 1251.28,
      "duration": 4.24
    },
    {
      "text": "that holding your breath the whole time",
      "start": 1253.52,
      "duration": 4.08
    },
    {
      "text": "guys i'm going i'm putting telegram back",
      "start": 1255.52,
      "duration": 5.12
    },
    {
      "text": "on putting tick tock tick tock back on",
      "start": 1257.6,
      "duration": 5.6
    },
    {
      "text": "and i will see you guys soon",
      "start": 1260.64,
      "duration": 5.039
    },
    {
      "text": "love you guys",
      "start": 1263.2,
      "duration": 2.479
    }
  ],
  "is_generated": true
}